Workbook
Name _ftn1: '7A'!$A$23
Name _ftnref1: '7A'!#REF!

Sheet Data Input
B1: Current Year | H1: 2022
B2: No of Year Audited | H2: 5
B3: No of Year Projected (Excl. current year) | H3: 2
A4: Name of Party | B4: H R Ispat Pvt Ltd
A5: Name of Bank | B5: Punjab National Bank
A6: Name of Branch | B6: MCC Durgapur
A7: Name of CO | B7: Durgapur
C8: 5 | D8: 4 | E8: 3 | F8: 2 | G8: 1 | H8: 0 | I8: 1 | J8: 2 | K8: 3 | L8: 3
C9: =+IF($H$2<C8,0,1) -> 1 | D9: =+IF($H$2<D8,0,1) -> 1 | E9: =+IF($H$2<E8,0,1) -> 1 | F9: =+IF($H$2<F8,0,1) -> 1 | G9: =+IF($H$2<G8,0,1) -> 1 | H9: 1 | I9: =+IF(I8<=$H$3, 1, 0) -> 1 | J9: =+IF(J8<=$H$3, 1, 0) -> 1 | K9: =+IF(K8<=$H$3, 1, 0) -> 0 | L9: =+IF(L8<=$H$3, 1, 0) -> 0
C10: Audited | D10: Audited | E10: Audited | F10: Audited | G10: Audited | H10: Audited | I10: Audited | J10: Audited | K10: Projected | L10: Projected
B11: YEAR ENDING 31ST MARCH | C11: =IF(D11="", "", D11-1) -> 2017 | D11: =IF(E11="", "", E11-1) -> 2018 | E11: =IF(F11="", "", F11-1) -> 2019 | F11: =IF(G11="", "", G11-1) -> 2020 | G11: =IF(H11="", "", H11-1) -> 2021 | H11: =+IF(H1="", "", H1) -> 2022 | I11: =IF(H11="", "", H11+1) -> 2023 | J11: =IF(I11="", "", I11+1) -> 2024 | K11: =IF(J11="", "", J11+1) -> 2025 | L11: =IF(K11="", "", K11+1) -> 2026
B12: GROSS SALES | C12: =SUM(C13:C14) -> 0 | D12: =SUM(D13:D14) -> 0 | E12: =SUM(E13:E14) -> 0 | F12: =SUM(F13:F14) -> 0 | G12: =SUM(G13:G14) -> 0 | H12: =SUM(H13:H14) -> 0 | I12: =SUM(I13:I14) -> 564.38 | J12: =SUM(J13:J14) -> 471.12 | ... L12: =SUM(L13:L14) -> 603.94
B13: Domestic Sales | I13: 564.38 | J13: 471.12 | K13: 528.88 | L13: 603.94
B14: Exports Sales
B15: Other Operating INCOME
B16: TOTAL | C16: =SUM(C13:C15) -> 0 | D16: =SUM(D13:D15) -> 0 | E16: =SUM(E13:E15) -> 0 | F16: =SUM(F13:F15) -> 0 | G16: =SUM(G13:G15) -> 0 | H16: =SUM(H13:H15) -> 0 | I16: =SUM(I13:I15) -> 564.38 | J16: =SUM(J13:J15) -> 471.12 | ... L16: =SUM(L13:L15) -> 603.94
B17: Less: Excise Duty / taxes
B18: NET SALES | C18: =C16-C17 -> 0 | D18: =D16-D17 -> 0 | E18: =E16-E17 -> 0 | F18: =F16-F17 -> 0 | G18: =G16-G17 -> 0 | H18: =H16-H17 -> 0 | I18: =I16-I17 -> 564.38 | J18: =J16-J17 -> 471.12 | ... L18: =L16-L17 -> 603.94
B19: % rise/fall in Net Sales compared to Previous Year | C19: - | D19: =(D18-C18)/C18 -> #DIV/0! | E19: =(E18-D18)/D18 -> #DIV/0! | F19: =(F18-E18)/E18 -> #DIV/0! | G19: =(G18-F18)/F18 -> #DIV/0! | H19: =(H18-G18)/G18 -> #DIV/0! | I19: =(I18-H18)/H18 -> #DIV/0! | J19: =(J18-I18)/I18 -> -0.16524328 | K19: =(K18-J18)/J18 -> 0.12260146 | L19: =(L18-K18)/K18 -> 0.14192255
B20: COST OF SALES
B21: Raw Materials consumption | C21: =IF((C22+C23)="", "", C22+C23) -> 0 | D21: =IF((D22+D23)="", "", D22+D23) -> 0 | E21: =IF((E22+E23)="", "", E22+E23) -> 0 | F21: =IF((F22+F23)="", "", F22+F23) -> 0 | G21: =IF((G22+G23)="", "", G22+G23) -> 0 | H21: =IF((H22+H23)="", "", H22+H23) -> 0 | I21: =IF((I22+I23)="", "", I22+I23) -> 473.14 | J21: =IF((J22+J23)="", "", J22+J23) -> 384.37 | ... L21: =IF((L22+L23)="", "", L22+L23) -> 491.28
B22: a) Import
B23: b) Indigenous | I23: 473.14 | J23: 384.37 | K23: 435.88 | L23: 491.28
B24: Other Spares/packing Material / trading goods | I24: 11.37 | J24: 8.3 | K24: 9.81 | L24: 11.05
B25: Indigenous packing material (Incl. Stores)
B26: Power & Fuel | I26: 71.29 | J26: 61.98 | K26: 70.35 | L26: 80
B27: Direct Cost | I27: 0.8 | J27: 0.89 | K27: 1.63 | L27: 1.79
B28: Other Mfg. Expenses | I28: =0.03+1.17 -> 1.2 | J28: =0.05+0.98 -> 1.03 | K28: 1.08 | L28: 1.19
B29: Depreciation | I29: 3.23 | J29: 3.47 | K29: 3.4 | L29: 3.4
B30: Sub total | C30: =SUM(C24:C29)+C21 -> 0 | D30: =SUM(D24:D29)+D21 -> 0 | E30: =SUM(E24:E29)+E21 -> 0 | F30: =SUM(F24:F29)+F21 -> 0 | G30: =SUM(G24:G29)+G21 -> 0 | H30: =SUM(H24:H29)+H21 -> 0 | I30: =SUM(I24:I29)+I21 -> 561.03 | J30: =SUM(J24:J29)+J21 -> 460.04 | ... L30: =SUM(L24:L29)+L21 -> 588.71
B31: INCREASE / (DECREASE) IN STOCKS
B32: ADD: Opening Stock in Process
B33: Sub Total | C33: =C30+C32 -> 0 | D33: =D30+D32 -> 0 | E33: =E30+E32 -> 0 | F33: =F30+F32 -> 0 | G33: =G30+G32 -> 0 | H33: =H30+H32 -> 0 | I33: =I30+I32 -> 561.03 | J33: =J30+J32 -> 460.04 | ... L33: =L30+L32 -> 588.71
B34: Deduct: Closing Stock in Process
B35: COST OF PRODUCTION | C35: =C33-C34 -> 0 | D35: =D33-D34 -> 0 | E35: =E33-E34 -> 0 | F35: =F33-F34 -> 0 | G35: =G33-G34 -> 0 | H35: =H33-H34 -> 0 | I35: =I33-I34 -> 561.03 | J35: =J33-J34 -> 460.04 | ... L35: =L33-L34 -> 588.71
B36: ADD: Opening Stock of Finished Goods | I36: 11.09 | J36: 22.59 | K36: 25.66 | L36: 36.36
B37: Sub Total | C37: =C35+C36 -> 0 | D37: =D35+D36 -> 0 | E37: =E35+E36 -> 0 | F37: =F35+F36 -> 0 | G37: =G35+G36 -> 0 | H37: =H35+H36 -> 0 | I37: =I35+I36 -> 572.12 | J37: =J35+J36 -> 482.63 | ... L37: =L35+L36 -> 625.07
B38: LESS: Closing Stock of Finished Goods | I38: 22.59 | J38: 25.66 | K38: 36.36 | L38: 41.34
B39: COST OF SALES | C39: =C37-C38 -> 0 | D39: =D37-D38 -> 0 | E39: =E37-E38 -> 0 | F39: =F37-F38 -> 0 | G39: =G37-G38 -> 0 | H39: =H37-H38 -> 0 | I39: =I37-I38 -> 549.53 | J39: =J37-J38 -> 456.97 | ... L39: =L37-L38 -> 583.73
B40: Selling, General & Admn. Expenses/Fin. Charges | C40: =+SUM(C41:C43) -> 0 | D40: =+SUM(D41:D43) -> 0 | E40: =+SUM(E41:E43) -> 0 | F40: =+SUM(F41:F43) -> 0 | G40: =+SUM(G41:G43) -> 0 | H40: =+SUM(H41:H43) -> 0 | I40: =+SUM(I41:I43) -> 1.92 | J40: =+SUM(J41:J43) -> 3.6 | ... L40: =+SUM(L41:L43) -> 3.62
B41: a) Selling Expenses
B42: b) General & admin Exp/ Finance Expenses | I42: =85.28-I26-I24-I28 -> 1.42 | J42: =74.32-J26-J24-J28 -> 3.01 | K42: 3.17 | L42: 3.62
B43: c) Employee Benefit Expenses | I43: =0.4+0.1 -> 0.5 | J43: =0.48+0.11 -> 0.59
B44: SUB TOTAL | C44: =C39+C40 -> 0 | D44: =D39+D40 -> 0 | E44: =E39+E40 -> 0 | F44: =F39+F40 -> 0 | G44: =G39+G40 -> 0 | H44: =H39+H40 -> 0 | I44: =I39+I40 -> 551.45 | J44: =J39+J40 -> 460.57 | ... L44: =L39+L40 -> 587.35
B45: Operating Profit before Interest | C45: =C18-C44 -> 0 | D45: =D18-D44 -> 0 | E45: =E18-E44 -> 0 | F45: =F18-F44 -> 0 | G45: =G18-G44 -> 0 | H45: =H18-H44 -> 0 | I45: =I18-I44 -> 12.93 | J45: =J18-J44 -> 10.55 | ... L45: =L18-L44 -> 16.59
B46: Interest | C46: =SUM(C47:C49) -> 0 | D46: =SUM(D47:D49) -> 0 | E46: =SUM(E47:E49) -> 0 | F46: =SUM(F47:F49) -> 0 | G46: =SUM(G47:G49) -> 0 | H46: =SUM(H47:H49) -> 0 | I46: =SUM(I47:I49) -> 2.45 | J46: =SUM(J47:J49) -> 3.69 | ... L46: =SUM(L47:L49) -> 4.71
B47: a) Term Loan (incl. other term liabilities) | I47: 0.5 | J47: 0.6 | K47: 0.21 | L47: 0.12
B48: b) Working Capital | I48: 1.95 | J48: 3.09 | K48: 4.59 | L48: 4.59
B49: c) Other Charges
B50: Operating Profit After Interest | C50: =C45-C46 -> 0 | D50: =D45-D46 -> 0 | E50: =E45-E46 -> 0 | F50: =F45-F46 -> 0 | G50: =G45-G46 -> 0 | H50: =H45-H46 -> 0 | I50: =I45-I46 -> 10.48 | J50: =J45-J46 -> 6.86 | ... L50: =L45-L46 -> 11.88
B51: ADD: Non-Operating Income | I51: 0.1 | J51: 0.15
B52: LESS: Non-Operating Expenditure
B53: Net of Non-Operating Income & Expenditure | C53: =C51-C52 -> 0 | D53: =D51-D52 -> 0 | E53: =E51-E52 -> 0 | F53: =F51-F52 -> 0 | G53: =G51-G52 -> 0 | H53: =H51-H52 -> 0 | I53: =I51-I52 -> 0.1 | J53: =J51-J52 -> 0.15 | K53: 0.2 | L53: 0.22
B54: PROFIT BEFORE TAX | C54: =C50+C53 -> 0 | D54: =D50+D53 -> 0 | E54: =E50+E53 -> 0 | F54: =F50+F53 -> 0 | G54: =G50+G53 -> 0 | H54: =H50+H53 -> 0 | I54: =I50+I53 -> 10.58 | J54: =J50+J53 -> 7.01 | ... L54: =L50+L53 -> 12.1
B55: Provision for Taxation | I55: =3.78+1.5+0.05 -> 5.33 | J55: =1.72+0.28+0.22 -> 2.22 | K55: =2.56+0.26 -> 2.82 | L55: =3.55+0.43 -> 3.98
B56: Deferred Tax
B57: NET PROFIT | C57: =C54-(C55+C56) -> 0 | D57: =D54-(D55+D56) -> 0 | E57: =E54-(E55+E56) -> 0 | F57: =F54-(F55+F56) -> 0 | G57: =G54-(G55+G56) -> 0 | H57: =H54-(H55+H56) -> 0 | I57: =I54-(I55+I56) -> 5.25 | J57: =J54-(J55+J56) -> 4.79 | ... L57: =L54-(L55+L56) -> 8.12
B58: Dividend on Equity | C58: =+C57*C59 -> 0 | D58: =+D57*D59 -> 0 | E58: =+E57*E59 -> 0 | F58: =+F57*F59 -> 0 | G58: =+G57*G59 -> 0 | H58: =+H57*H59 -> 0 | I58: =+I57*I59 -> 0 | J58: =+J57*J59 -> 0 | ... L58: =+L57*L59 -> 0
B59: Dividend Rate | E59: 0 | F59: 0 | G59: 0 | H59: 0 | I59: 0 | J59: 0 | K59: 0 | L59: 0
B60: Retained profit ( 13 - 14 ) | C60: =C57-C58 -> 0 | D60: =D57-D58 -> 0 | E60: =E57-E58 -> 0 | F60: =F57-F58 -> 0 | G60: =G57-G58 -> 0 | H60: =H57-H58 -> 0 | I60: =I57-I58 -> 5.25 | J60: =J57-J58 -> 4.79 | ... L60: =L57-L58 -> 8.12
B61: Retained Profit/Net Profit % | C61: =C60/C57% -> #DIV/0! | D61: =D60/D57% -> #DIV/0! | E61: =E60/E57% -> #DIV/0! | F61: =F60/F57% -> #DIV/0! | G61: =G60/G57% -> #DIV/0! | H61: =H60/H57% -> #DIV/0! | I61: =I60/I57% -> 100 | J61: =J60/J57% -> 100 | ... L61: =L60/L57% -> 100
B62: Cash Profit | C62: =C57+C29 -> 0 | D62: =D57+D29 -> 0 | F62: =F57+F29 -> 0 | G62: =G57+G29 -> 0 | H62: =H57+H29+H56 -> 0 | I62: =I57+I29+I56 -> 8.48 | J62: =J57+J29+J56 -> 8.26 | K62: =K57+K29+K56 -> 10.24 | L62: =L57+L29+L56 -> 11.52
B63: Operating Profit % | C63: =C57/C18% -> #DIV/0! | D63: =D57/D18% -> #DIV/0! | F63: =F57/F18% -> #DIV/0! | G63: =G57/G18% -> #DIV/0! | H63: =H57/H18% -> #DIV/0! | I63: =I57/I18% -> 0.93022432 | J63: =J57/J18% -> 1.0167261 | K63: =K57/K18% -> 1.293299 | L63: =L57/L18% -> 1.3445044
B64: Interest coveratio ration (Intt / NP) | D64: =D46/D57 -> #DIV/0! | F64: =F46/F57 -> #DIV/0! | G64: =G46/G57 -> #DIV/0! | H64: =H46/H57 -> #DIV/0! | I64: =I46/I57 -> 0.46666667 | J64: =J46/J57 -> 0.77035491 | K64: =K46/K57 -> 0.70175439 | L64: =L46/L57 -> 0.58004926
B65: INCREASE / DECREASE IN STOCKS | C65: =(C34+C38)-(C32+C36) -> 0 | D65: =(D34+D38)-(D32+D36) -> 0 | F65: =(F34+F38)-(F32+F36) -> 0 | G65: =(G34+G38)-(G32+G36) -> 0 | H65: =(H34+H38)-(H32+H36) -> 0 | I65: =(I34+I38)-(I32+I36) -> 11.5 | J65: =(J34+J38)-(J32+J36) -> 3.07 | K65: =(K34+K38)-(K32+K36) -> 10.7 | L65: =(L34+L38)-(L32+L36) -> 4.98
B66: Inventory + Receivables / Sales % | D66: =(D109+D111+D113+D116+D117+D118)/D18% -> #DIV/0! | F66: =(F109+F111+F113+F116+F117+F118)/F18% -> #DIV/0! | G66: =(G109+G111+G113+G116+G117+G118)/G18% -> #DIV/0! | H66: =(H109+H111+H113+H116+H117+H118)/H18% -> #DIV/0! | I66: =(I109+I111+I113+I116+I117+I118)/I18% -> 9.7895035 | J66: =(J109+J111+J113+J116+J117+J118)/J18% -> 13.962472 | K66: =(K109+K111+K113+K116+K117+K118)/K18% -> 17.864166 | L66: =(L109+L111+L113+L116+L117+L118)/L18% -> 17.834553
B68: CURRENT LIABILITIES
B69: Working Capital from other banks
B70: Working Capital from our Bank (Existing/ Proposed) | I70: 19.15 | J70: 34.51 | K70: 70 | L70: 70
B71: i) of which LC Discounted HDFC
B72: ii) of Which PC/ PS
B73: iii) of which BP/BD (Buyers credit)
B74: SUB-TOTAL (A) | C74: =C70+C69 -> 0 | D74: =D70+D69 -> 0 | E74: =E70+E69 -> 0 | F74: =F70+F69 -> 0 | G74: =G70+G69 -> 0 | H74: =H70+H69 -> 0 | I74: =I70+I69 -> 19.15 | J74: =J70+J69 -> 34.51 | ... L74: =L70+L69 -> 70
B75: Sundry Creditors for Trade | I75: 17.22 | J75: 10.35 | K75: =6+4.47 -> 10.47 | L75: =4.94+6.82 -> 11.76
B76: Sundry Creditors for Expenses
B77: Sundry Creditors for LC
B78: Advances From Customers/Deposits
B79: Term Loan installments due within 1 year | I79: 2.42 | J79: 2.39 | K79: 1.02 | L79: 1.02
B80: Provision for Taxation
B81: Divident Payable
B82: Share Application Money/ Warrant/ Unsecured Loan - ST
B83: Other Statutory Liabilities
B84: Other Current Liabilities & provisions due with in 1 Year | I84: 15.31 | J84: 12.03 | K84: 7.56 | L84: =5.25+3.55 -> 8.8
B85: SUB-TOTAL (B) | C85: =SUM(C75:C84) -> 0 | D85: =SUM(D75:D84) -> 0 | E85: =SUM(E75:E84) -> 0 | F85: =SUM(F75:F84) -> 0 | G85: =SUM(G75:G84) -> 0 | H85: =SUM(H75:H84) -> 0 | I85: =SUM(I75:I84) -> 34.95 | J85: =SUM(J75:J84) -> 24.77 | ... L85: =SUM(L75:L84) -> 21.58
B86: TOTAL CURRENT LIABILITIES (A+B) | C86: =C74+C85 -> 0 | D86: =D74+D85 -> 0 | E86: =E74+E85 -> 0 | F86: =F74+F85 -> 0 | G86: =G74+G85 -> 0 | H86: =H74+H85 -> 0 | I86: =I74+I85 -> 54.1 | J86: =J74+J85 -> 59.28 | ... L86: =L74+L85 -> 91.58
B87: TERM LIABILITIES
B88: Debentures @ 12%
B89: Term Loans | I89: 3.73 | J89: 2.08 | K89: 1.13 | L89: 0.11
B90: Unsecured Loans from promoters & relatives | I90: 2.78 | J90: 3.2 | K90: 3.2 | L90: 3.2
B91: Intercorportae deposits
B92: Other Term Liabilities | I92: 5.17 | J92: 3.7 | K92: 3.7 | L92: 3.7
B93: Quasi capital (unsecured loan from promoters)
B94: TOTAL TERM LIABILITIES | C94: =SUM(C88:C93) -> 0 | D94: =SUM(D88:D93) -> 0 | E94: =SUM(E88:E93) -> 0 | F94: =SUM(F88:F93) -> 0 | G94: =SUM(G88:G93) -> 0 | H94: =SUM(H88:H93) -> 0 | I94: =SUM(I88:I93) -> 11.68 | J94: =SUM(J88:J93) -> 8.98 | ... L94: =SUM(L88:L93) -> 7.01
B95: TOTAL OUTSIDE LIABILITIES | C95: =C86+C94 -> 0 | D95: =D86+D94 -> 0 | E95: =E86+E94 -> 0 | F95: =F86+F94 -> 0 | G95: =G86+G94 -> 0 | H95: =H86+H94 -> 0 | I95: =I86+I94 -> 65.78 | J95: =J86+J94 -> 68.26 | ... L95: =L86+L94 -> 98.59
B96: Ordinary Share Capital | I96: 5.33 | J96: 5.33 | K96: 5.33 | L96: 5.33
B97: General Reserve excl. revaluation reserve | I97: 31.83 | J97: 36.62 | K97: =8.68+34.78 -> 43.46 | L97: =8.68+42.9 -> 51.58
B98: Capital reserve
B99: Deferred Tax Liability | I99: 2 | J99: 2.22 | K99: 2.48 | L99: 2.91
B100: Profit & Loss account | C100: =+C60 -> 0 | D100: =+D60 -> 0
B101: NET WORTH | C101: =SUM(C96:C100) -> 0 | D101: =SUM(D96:D100) -> 0 | E101: =SUM(E96:E100) -> 0 | F101: =SUM(F96:F100) -> 0 | G101: =SUM(G96:G100) -> 0 | H101: =SUM(H96:H100) -> 0 | I101: =SUM(I96:I100) -> 39.16 | J101: =SUM(J96:J100) -> 44.17 | ... L101: =SUM(L96:L100) -> 59.82
...

Sheet Sheet3
A1: Column1 | B1: 2023 | C1: 2024 | D1: 2025 | E1: 2026
A2: YEAR ENDING 31ST MARCH | B2: Audited | C2: Audited | D2: Projected | E2: Projected
A3: GROSS SALES | B3: 564.38 | C3: 471.12 | D3: 528.88 | E3: 603.94
A4: Domestic Sales | B4: 564.38 | C4: 471.12 | D4: 528.88 | E4: 603.94
A5: Exports Sales
A6: Other Operating INCOME
A7: TOTAL | B7: 564.38 | C7: 471.12 | D7: 528.88 | E7: 603.94
A8: Less: Excise Duty / taxes
A9: NET SALES | B9: 564.38 | C9: 471.12 | D9: 528.88 | E9: 603.94
A10: % rise/fall in Net Sales compared to Previous Year | B10: #DIV/0! | C10: -0.16524328 | D10: 0.12260146 | E10: 0.14192255
A11: COST OF SALES
A12: Raw Materials consumption | B12: 473.14 | C12: 384.37 | D12: 435.88 | E12: 491.28
A13: a) Import
A14: b) Indigenous | B14: 473.14 | C14: 384.37 | D14: 435.88 | E14: 491.28
A15: Other Spares/packing Material / trading goods | B15: 11.37 | C15: 8.3 | D15: 9.81 | E15: 11.05
A16: Indigenous packing material (Incl. Stores)
A17: Power & Fuel | B17: 71.29 | C17: 61.98 | D17: 70.35 | E17: 80
A18: Direct Cost | B18: 0.8 | C18: 0.89 | D18: 1.63 | E18: 1.79
A19: Other Mfg. Expenses | B19: 1.2 | C19: 1.03 | D19: 1.08 | E19: 1.19
A20: Depreciation | B20: 3.23 | C20: 3.47 | D20: 3.4 | E20: 3.4
A21: Sub total | B21: 561.03 | C21: 460.04 | D21: 522.15 | E21: 588.71
A22: INCREASE / (DECREASE) IN STOCKS
A23: ADD: Opening Stock in Process
A24: Sub Total | B24: 561.03 | C24: 460.04 | D24: 522.15 | E24: 588.71
A25: Deduct: Closing Stock in Process
A26: COST OF PRODUCTION | B26: 561.03 | C26: 460.04 | D26: 522.15 | E26: 588.71
A27: ADD: Opening Stock of Finished Goods | B27: 11.09 | C27: 22.59 | D27: 25.66 | E27: 36.36
A28: Sub Total | B28: 572.12 | C28: 482.63 | D28: 547.81 | E28: 625.07
A29: LESS: Closing Stock of Finished Goods | B29: 22.59 | C29: 25.66 | D29: 36.36 | E29: 41.34
A30: COST OF SALES | B30: 549.53 | C30: 456.97 | D30: 511.45 | E30: 583.73
A31: Selling, General & Admn. Expenses/Fin. Charges | B31: 1.92 | C31: 3.6 | D31: 3.17 | E31: 3.62
A32: a) Selling Expenses
A33: b) General & admin Exp/ Finance Expenses | B33: 1.42 | C33: 3.01 | D33: 3.17 | E33: 3.62
A34: c) Employee Benefit Expenses | B34: 0.5 | C34: 0.59
A35: SUB TOTAL | B35: 551.45 | C35: 460.57 | D35: 514.62 | E35: 587.35
A36: Operating Profit before Interest | B36: 12.93 | C36: 10.55 | D36: 14.26 | E36: 16.59
A37: Interest | B37: 2.45 | C37: 3.69 | D37: 4.8 | E37: 4.71
A38: a) Term Loan (incl. other term liabilities) | B38: 0.5 | C38: 0.6 | D38: 0.21 | E38: 0.12
A39: b) Working Capital | B39: 1.95 | C39: 3.09 | D39: 4.59 | E39: 4.59
A40: c) Other Charges
A41: Operating Profit After Interest | B41: 10.48 | C41: 6.86 | D41: 9.46 | E41: 11.88
A42: ADD: Non-Operating Income | B42: 0.1 | C42: 0.15
A43: LESS: Non-Operating Expenditure
A44: Net of Non-Operating Income & Expenditure | B44: 0.1 | C44: 0.15 | D44: 0.2 | E44: 0.22
A45: PROFIT BEFORE TAX | B45: 10.58 | C45: 7.01 | D45: 9.66 | E45: 12.1
A46: Provision for Taxation | B46: 5.33 | C46: 2.22 | D46: 2.82 | E46: 3.98
A47: Deferred Tax
A48: NET PROFIT | B48: 5.25 | C48: 4.79 | D48: 6.84 | E48: 8.12
A49: Dividend on Equity | B49: 0 | C49: 0 | D49: 0 | E49: 0
A50: Dividend Rate | B50: 0 | C50: 0 | D50: 0 | E50: 0
A51: Retained profit ( 13 - 14 ) | B51: 5.25 | C51: 4.79 | D51: 6.84 | E51: 8.12
A52: Retained Profit/Net Profit % | B52: 100 | C52: 100 | D52: 100 | E52: 100
A53: Cash Profit | B53: 8.48 | C53: 8.26 | D53: 10.24 | E53: 11.52
A54: Operating Profit % | B54: 0.93022432 | C54: 1.0167261 | D54: 1.293299 | E54: 1.3445044
A55: Interest coveratio ration (Intt / NP) | B55: 0.46666667 | C55: 0.77035491 | D55: 0.70175439 | E55: 0.58004926
A56: INCREASE / DECREASE IN STOCKS | B56: 11.5 | C56: 3.07 | D56: 10.7 | E56: 4.98
A57: Inventory + Receivables / Sales % | B57: 9.7895035 | C57: 13.962472 | D57: 17.864166 | E57: 17.834553
A59: CURRENT LIABILITIES
A60: Working Capital from other banks
A61: Working Capital from our Bank (Existing/ Proposed) | B61: 19.15 | C61: 34.51 | D61: 70 | E61: 70
A62: i) of which LC Discounted HDFC
A63: ii) of Which PC/ PS
A64: iii) of which BP/BD (Buyers credit)
A65: SUB-TOTAL (A) | B65: 19.15 | C65: 34.51 | D65: 70 | E65: 70
A66: Sundry Creditors for Trade | B66: 17.22 | C66: 10.35 | D66: 10.47 | E66: 11.76
A67: Sundry Creditors for Expenses
A68: Sundry Creditors for LC
A69: Advances From Customers/Deposits
A70: Term Loan installments due within 1 year | B70: 2.42 | C70: 2.39 | D70: 1.02 | E70: 1.02
A71: Provision for Taxation
A72: Divident Payable
A73: Share Application Money/ Warrant/ Unsecured Loan - ST
A74: Other Statutory Liabilities
A75: Other Current Liabilities & provisions due with in 1 Year | B75: 15.31 | C75: 12.03 | D75: 7.56 | E75: 8.8
A76: SUB-TOTAL (B) | B76: 34.95 | C76: 24.77 | D76: 19.05 | E76: 21.58
A77: TOTAL CURRENT LIABILITIES (A+B) | B77: 54.1 | C77: 59.28 | D77: 89.05 | E77: 91.58
A78: TERM LIABILITIES
A79: Debentures @ 12%
A80: Term Loans | B80: 3.73 | C80: 2.08 | D80: 1.13 | E80: 0.11
A81: Unsecured Loans from promoters & relatives | B81: 2.78 | C81: 3.2 | D81: 3.2 | E81: 3.2
A82: Intercorportae deposits
A83: Other Term Liabilities | B83: 5.17 | C83: 3.7 | D83: 3.7 | E83: 3.7
A84: Quasi capital (unsecured loan from promoters)
A85: TOTAL TERM LIABILITIES | B85: 11.68 | C85: 8.98 | D85: 8.03 | E85: 7.01
A86: TOTAL OUTSIDE LIABILITIES | B86: 65.78 | C86: 68.26 | D86: 97.08 | E86: 98.59
A87: Ordinary Share Capital | B87: 5.33 | C87: 5.33 | D87: 5.33 | E87: 5.33
A88: General Reserve excl. revaluation reserve | B88: 31.83 | C88: 36.62 | D88: 43.46 | E88: 51.58
A89: Capital reserve
A90: Deferred Tax Liability | B90: 2 | C90: 2.22 | D90: 2.48 | E90: 2.91
A91: Profit & Loss account
A92: NET WORTH | B92: 39.16 | C92: 44.17 | D92: 51.27 | E92: 59.82
A93: TOTAL LIABILITIES | B93: 104.94 | C93: 112.43 | D93: 148.35 | E93: 158.41
A95: CURRENT ASSETS
A96: Cash & Bank Balances | B96: 2.81 | C96: 5.02 | D96: 6.17 | E96: 12.16
A97: Investments (Other than Long Term) | B97: 0 | C97: 0 | D97: 0 | E97: 0
A98: a) Govt. & Other Securities
A99: b) Fixed Deposits (Banks) - Un encumbered
A100: Receivables | B100: 18.81 | C100: 30.67 | D100: 37.04 | E100: 42.29
A101: - Other than deferred & Exports <6M | B101: 18.81 | C101: 30.67 | D101: 37.04 | E101: 42.29
A102: - Export Receivables <6M
...

Sheet MPBF
A1: =+'Data Input'!B5 -> Punjab National Bank
A2: =+'Data Input'!B6 -> MCC Durgapur
A3: =+'Data Input'!B7 -> Durgapur
A4: =+'Data Input'!B4 -> H R Ispat Pvt Ltd | B4: =IF('Data Input'!E10="", "", 'Data Input'!E10) -> Audited | C4: =IF('Data Input'!F10="", "", 'Data Input'!F10) -> Audited | D4: =IF('Data Input'!G10="", "", 'Data Input'!G10) -> Audited | E4: =IF('Data Input'!H10="", "", 'Data Input'!H10) -> Audited | F4: =IF('Data Input'!I10="", "", 'Data Input'!I10) -> Audited | G4: =IF('Data Input'!J10="", "", 'Data Input'!J10) -> Audited | H4: =IF('Data Input'!K10="", "", 'Data Input'!K10) -> Projected | I4: =IF('Data Input'!L10="", "", 'Data Input'!L10) -> Projected
B5: =IF('Data Input'!E11="", "", 'Data Input'!E11) -> 2019 | C5: =IF('Data Input'!F11="", "", 'Data Input'!F11) -> 2020 | D5: =IF('Data Input'!G11="", "", 'Data Input'!G11) -> 2021 | E5: =IF('Data Input'!H11="", "", 'Data Input'!H11) -> 2022 | F5: =IF('Data Input'!I11="", "", 'Data Input'!I11) -> 2023 | G5: =IF('Data Input'!J11="", "", 'Data Input'!J11) -> 2024 | H5: =IF('Data Input'!K11="", "", 'Data Input'!K11) -> 2025 | I5: =IF('Data Input'!L11="", "", 'Data Input'!L11) -> 2026
A6: 1. Sales/ Income :-
A7: Gross Sales | B7: ='Data Input'!E12 -> 0 | C7: ='Data Input'!F12 -> 0 | D7: ='Data Input'!G12 -> 0 | E7: ='Data Input'!H12 -> 0 | F7: ='Data Input'!I12 -> 564.38 | G7: ='Data Input'!J12 -> 471.12 | H7: ='Data Input'!K12 -> 528.88 | I7: ='Data Input'!L12 -> 603.94
A8: Net Sales | B8: ='Data Input'!E18 -> 0 | C8: ='Data Input'!F18 -> 0 | D8: ='Data Input'!G18 -> 0 | E8: ='Data Input'!H18 -> 0 | F8: ='Data Input'!I18 -> 564.38 | G8: ='Data Input'!J18 -> 471.12 | H8: ='Data Input'!K18 -> 528.88 | I8: ='Data Input'!L18 -> 603.94
A9: Domestic Sales | B9: ='Data Input'!E13 -> 0 | C9: ='Data Input'!F13 -> 0 | D9: ='Data Input'!G13 -> 0 | E9: ='Data Input'!H13 -> 0 | F9: ='Data Input'!I13 -> 564.38 | G9: ='Data Input'!J13 -> 471.12 | H9: ='Data Input'!K13 -> 528.88 | I9: ='Data Input'!L13 -> 603.94
A10: Export Sales | B10: ='Data Input'!E14 -> 0 | C10: ='Data Input'!F14 -> 0 | D10: ='Data Input'!G14 -> 0 | E10: ='Data Input'!H14 -> 0 | F10: ='Data Input'!I14 -> 0 | G10: ='Data Input'!J14 -> 0 | H10: ='Data Input'!K14 -> 0 | I10: ='Data Input'!L14 -> 0
A11: =+'[1]P & L A'!A16 -> Total Receipts | B11: =+B7+'Data Input'!E51 -> 0 | C11: =+C7+'Data Input'!F51 -> 0 | D11: =+D7+'Data Input'!G51 -> 0 | E11: =+E7+'Data Input'!H51 -> 0 | F11: =+F7+'Data Input'!I51 -> 564.48 | G11: =+G7+'Data Input'!J51 -> 471.27 | H11: =+H7+'Data Input'!K51 -> 528.88 | I11: =+I7+'Data Input'!L51 -> 603.94
A12: Total Expenses | B12: =B11-'Data Input'!E50+'Data Input'!E52 -> 0 | C12: =C11-'Data Input'!F50+'Data Input'!F52 -> 0 | D12: =D11-'Data Input'!G50+'Data Input'!G52 -> 0 | E12: =E11-'Data Input'!H50+'Data Input'!H52 -> 0 | F12: =F11-'Data Input'!I50+'Data Input'!I52 -> 554 | G12: =G11-'Data Input'!J50+'Data Input'!J52 -> 464.41 | H12: =H11-'Data Input'!K50+'Data Input'!K52 -> 519.42 | I12: =I11-'Data Input'!L50+'Data Input'!L52 -> 592.06
A13: Cost of Production | B13: ='Data Input'!E35 -> 0 | C13: ='Data Input'!F35 -> 0 | D13: ='Data Input'!G35 -> 0 | E13: ='Data Input'!H35 -> 0 | F13: ='Data Input'!I35 -> 561.03 | G13: ='Data Input'!J35 -> 460.04 | H13: ='Data Input'!K35 -> 522.15 | I13: ='Data Input'!L35 -> 588.71
A14: Cost of Sales | B14: ='Data Input'!E39 -> 0 | C14: ='Data Input'!F39 -> 0 | D14: ='Data Input'!G39 -> 0 | E14: ='Data Input'!H39 -> 0 | F14: ='Data Input'!I39 -> 549.53 | G14: ='Data Input'!J39 -> 456.97 | H14: ='Data Input'!K39 -> 511.45 | I14: ='Data Input'!L39 -> 583.73
A15: 2. Holding Position :-
A16: 1. Raw Materials & Consumable Spares | B16: ='Data Input'!E113+'Data Input'!E118 -> 0 | C16: ='Data Input'!F113+'Data Input'!F118 -> 0 | D16: ='Data Input'!G113+'Data Input'!G118 -> 0 | E16: ='Data Input'!H113+'Data Input'!H118 -> 0 | F16: ='Data Input'!I113+'Data Input'!I118 -> 13.85 | G16: ='Data Input'!J113+'Data Input'!J118 -> 9.45 | H16: ='Data Input'!K113+'Data Input'!K118 -> 21.08 | I16: ='Data Input'!L113+'Data Input'!L118 -> 24.08
A17: (Month's Consumption) | B17: =(B16*12)/('Data Input'!E21+'Data Input'!E24+'Data Input'!E25) -> #DIV/0! | C17: =(C16*12)/('Data Input'!F21+'Data Input'!F24+'Data Input'!F25) -> #DIV/0! | D17: =(D16*12)/('Data Input'!G21+'Data Input'!G24+'Data Input'!G25) -> #DIV/0! | E17: =E16*12/('Data Input'!H21+'Data Input'!H24+'Data Input'!H25) -> #DIV/0! | F17: =F16*12/('Data Input'!I21+'Data Input'!I24+'Data Input'!I25) -> 0.34302698 | G17: =G16*12/('Data Input'!J21+'Data Input'!J24+'Data Input'!J25) -> 0.28879212 | H17: =H16*12/('Data Input'!K21+'Data Input'!K24+'Data Input'!K25) -> 0.56756939 | I17: =I16*12/('Data Input'!L21+'Data Input'!L24+'Data Input'!L25) -> 0.57523938
A18: 2. Stock In Process | B18: ='Data Input'!E116 -> 0 | C18: ='Data Input'!F116 -> 0 | D18: ='Data Input'!G116 -> 0 | E18: ='Data Input'!H116 -> 0 | F18: ='Data Input'!I116 -> 0 | G18: ='Data Input'!J116 -> 0 | H18: ='Data Input'!K116 -> 0 | I18: ='Data Input'!L116 -> 0
A19: (Month's Cost of Production) | B19: =B18*12/B13 -> #DIV/0! | C19: =C18*12/C13 -> #DIV/0! | D19: =D18*12/D13 -> #DIV/0! | E19: =E18*12/E13 -> #DIV/0! | F19: =F18*12/F13 -> 0 | G19: =G18*12/G13 -> 0 | H19: =H18*12/H13 -> 0 | I19: =I18*12/I13 -> 0
A20: 3. Finished Goods | B20: ='Data Input'!E117 -> 0 | C20: ='Data Input'!F117 -> 0 | D20: ='Data Input'!G117 -> 0 | E20: ='Data Input'!H117 -> 0 | F20: ='Data Input'!I117 -> 22.59 | G20: ='Data Input'!J117 -> 25.66 | H20: ='Data Input'!K117 -> 36.36 | I20: ='Data Input'!L117 -> 41.34
A21: (Month's Cost of Sales) | B21: =B20*12/B14 -> #DIV/0! | C21: =C20*12/C14 -> #DIV/0! | D21: =D20*12/D14 -> #DIV/0! | E21: =E20*12/E14 -> #DIV/0! | F21: =F20*12/F14 -> 0.49329427 | G21: =G20*12/G14 -> 0.67382979 | H21: =H20*12/H14 -> 0.85310392 | I21: =I20*12/I14 -> 0.84984496
A22: 4. Recievables - Domestic | B22: ='Data Input'!E110+'Data Input'!E129 -> 0 | C22: ='Data Input'!F110+'Data Input'!F129 -> 0 | D22: ='Data Input'!G110+'Data Input'!G129 -> 0 | E22: ='Data Input'!H110+'Data Input'!H129 -> 0 | F22: ='Data Input'!I110+'Data Input'!I129 -> 18.81 | G22: ='Data Input'!J110+'Data Input'!J129 -> 30.67 | H22: ='Data Input'!K110+'Data Input'!K129 -> 37.04 | I22: ='Data Input'!L110+'Data Input'!L129 -> 42.29
A23: (Month's Domestic Sales) | B23: =B22*12/B9 -> #DIV/0! | C23: =C22*12/C9 -> #DIV/0! | D23: =D22*12/D9 -> #DIV/0! | E23: =E22*12/E9 -> #DIV/0! | F23: =F22*12/F9 -> 0.3999433 | G23: =G22*12/G9 -> 0.78120224 | H23: =H22*12/H9 -> 0.84041749 | I23: =I22*12/I9 -> 0.84028215
A24: 5. Export Recievables | B24: ='Data Input'!E111 -> 0 | C24: ='Data Input'!F111 -> 0 | D24: ='Data Input'!G111 -> 0 | E24: ='Data Input'!H111 -> 0 | F24: ='Data Input'!I111 -> 0 | G24: ='Data Input'!J111 -> 0 | H24: ='Data Input'!K111 -> 0 | I24: ='Data Input'!L111 -> 0
A25: (Month's Export Sales) | B25: =B24*12/B10 -> #DIV/0! | C25: =C24*12/C10 -> #DIV/0! | D25: =D24*12/D10 -> #DIV/0! | E25: =E24*12/E10 -> #DIV/0! | F25: =F24*12/F10 -> #DIV/0! | G25: =G24*12/G10 -> #DIV/0! | H25: =H24*12/H10 -> #DIV/0! | I25: =I24*12/I10 -> #DIV/0!
A26: 6. Loans & Advances | B26: ='Data Input'!E119+'Data Input'!E120 -> 0 | C26: ='Data Input'!F119+'Data Input'!F120 -> 0 | D26: ='Data Input'!G119+'Data Input'!G120 -> 0 | E26: ='Data Input'!H119+'Data Input'!H120 -> 0 | F26: ='Data Input'!I119+'Data Input'!I120 -> 8.5 | G26: ='Data Input'!J119+'Data Input'!J120 -> 6.8 | H26: ='Data Input'!K119+'Data Input'!K120 -> 16.28 | I26: ='Data Input'!L119+'Data Input'!L120 -> 10.52
A27: 7. All other Current Assets Incl. Cash/ Bank Balance | B27: ='Data Input'!E121+'Data Input'!E105+'Data Input'!E106 -> 0 | C27: ='Data Input'!F121+'Data Input'!F105+'Data Input'!F106 -> 0 | D27: ='Data Input'!G121+'Data Input'!G105+'Data Input'!G106 -> 0 | E27: ='Data Input'!H121+'Data Input'!H105+'Data Input'!H106 -> 0 | F27: ='Data Input'!I121+'Data Input'!I105+'Data Input'!I106 -> 2.81 | G27: ='Data Input'!J121+'Data Input'!J105+'Data Input'!J106 -> 5.02 | H27: ='Data Input'!K121+'Data Input'!K105+'Data Input'!K106 -> 6.17 | I27: ='Data Input'!L121+'Data Input'!L105+'Data Input'!L106 -> 12.16
A28: Total Current Assets | B28: =+B27+B26+B24+B22+B20+B18+B16 -> 0 | C28: =+C27+C26+C24+C22+C20+C18+C16 -> 0 | D28: =+D27+D26+D24+D22+D20+D18+D16 -> 0 | E28: =+E27+E26+E24+E22+E20+E18+E16 -> 0 | F28: =+F27+F26+F24+F22+F20+F18+F16 -> 66.56 | G28: =+G27+G26+G24+G22+G20+G18+G16 -> 77.6 | H28: =+H27+H26+H24+H22+H20+H18+H16 -> 116.93 | I28: =+I27+I26+I24+I22+I20+I18+I16 -> 130.39
A29: 3. Chargeable Current Assets
A30: Raw material | B30: ='Data Input'!E113 -> 0 | C30: ='Data Input'!F113 -> 0 | D30: ='Data Input'!G113 -> 0 | E30: ='Data Input'!H113 -> 0 | F30: ='Data Input'!I113 -> 13.38 | G30: ='Data Input'!J113 -> 8.97 | H30: ='Data Input'!K113 -> 20.1 | I30: ='Data Input'!L113 -> 22.97
A31: Consumable Spares | B31: ='Data Input'!E118 -> 0 | C31: ='Data Input'!F118 -> 0 | D31: ='Data Input'!G118 -> 0 | E31: ='Data Input'!H118 -> 0 | F31: ='Data Input'!I118 -> 0.47 | G31: ='Data Input'!J118 -> 0.48 | H31: ='Data Input'!K118 -> 0.98 | I31: ='Data Input'!L118 -> 1.11
A32: Stock in Process | B32: ='Data Input'!E116 -> 0 | C32: ='Data Input'!F116 -> 0 | D32: ='Data Input'!G116 -> 0 | E32: ='Data Input'!H116 -> 0 | F32: ='Data Input'!I116 -> 0 | G32: ='Data Input'!J116 -> 0 | H32: ='Data Input'!K116 -> 0 | I32: ='Data Input'!L116 -> 0
A33: Finished Goods | B33: ='Data Input'!E117 -> 0 | C33: ='Data Input'!F117 -> 0 | D33: ='Data Input'!G117 -> 0 | E33: ='Data Input'!H117 -> 0 | F33: ='Data Input'!I117 -> 22.59 | G33: ='Data Input'!J117 -> 25.66 | H33: ='Data Input'!K117 -> 36.36 | I33: ='Data Input'!L117 -> 41.34
A34: a. Total Inventory | B34: =SUM(B30:B33) -> 0 | C34: =SUM(C30:C33) -> 0 | D34: =SUM(D30:D33) -> 0 | E34: =SUM(E30:E33) -> 0 | F34: =SUM(F30:F33) -> 36.44 | G34: =SUM(G30:G33) -> 35.11 | H34: =SUM(H30:H33) -> 57.44 | I34: =SUM(I30:I33) -> 65.42
A35: b. Recievables | B35: =B22+B24 -> 0 | C35: =C22+C24 -> 0 | D35: =D22+D24 -> 0 | E35: =E22+E24 -> 0 | F35: =F22+F24 -> 18.81 | G35: =G22+G24 -> 30.67 | H35: =H22+H24 -> 37.04 | I35: =I22+I24 -> 42.29
A36: (Month's Dom. & Exp. Sales) | B36: =B35*12/(B9+B10) -> #DIV/0! | C36: =C35*12/(C9+C10) -> #DIV/0! | D36: =D35*12/(D9+D10) -> #DIV/0! | E36: =E35*12/(E9+E10) -> #DIV/0! | F36: =F35*12/(F9+F10) -> 0.3999433 | G36: =G35*12/(G9+G10) -> 0.78120224 | H36: =H35*12/(H9+H10) -> 0.84041749 | I36: =I35*12/(I9+I10) -> 0.84028215
A37: Total CCA (a+b)
A38: 4. Other Current Assets :-
A39: Cash and Bank Balance | B39: ='Data Input'!E105 -> 0 | C39: ='Data Input'!F105 -> 0 | D39: ='Data Input'!G105 -> 0 | E39: ='Data Input'!H105 -> 0 | F39: ='Data Input'!I105 -> 2.81 | G39: ='Data Input'!J105 -> 5.02 | H39: ='Data Input'!K105 -> 6.17 | I39: ='Data Input'!L105 -> 12.16
A40: Advances to Suppliers | B40: ='Data Input'!E119 -> 0 | C40: ='Data Input'!F119 -> 0 | D40: ='Data Input'!G119 -> 0 | E40: ='Data Input'!H119 -> 0 | F40: ='Data Input'!I119 -> 7.57 | G40: ='Data Input'!J119 -> 6.18 | H40: ='Data Input'!K119 -> 0 | I40: ='Data Input'!L119 -> 0
A41: Other Current Assets | B41: ='Data Input'!E120+'Data Input'!E121+'Data Input'!E106 -> 0 | C41: ='Data Input'!F120+'Data Input'!F121+'Data Input'!F106 -> 0 | D41: ='Data Input'!G120+'Data Input'!G121+'Data Input'!G106 -> 0 | E41: ='Data Input'!H120+'Data Input'!H121+'Data Input'!H106 -> 0 | F41: ='Data Input'!I120+'Data Input'!I121+'Data Input'!I106 -> 0.93 | G41: ='Data Input'!J120+'Data Input'!J121+'Data Input'!J106 -> 0.62 | H41: ='Data Input'!K120+'Data Input'!K121+'Data Input'!K106 -> 16.28 | I41: ='Data Input'!L120+'Data Input'!L121+'Data Input'!L106 -> 10.52
A42: Total Other Current Assets | B42: =SUM(B39:B41) -> 0 | C42: =SUM(C39:C41) -> 0 | D42: =SUM(D39:D41) -> 0 | E42: =SUM(E39:E41) -> 0 | F42: =SUM(F39:F41) -> 11.31 | G42: =SUM(G39:G41) -> 11.82 | H42: =SUM(H39:H41) -> 22.45 | I42: =SUM(I39:I41) -> 22.68
A43: 5. Current Liabilities :-
A44: Sundry Creditors - General (Trade & LC) | B44: ='Data Input'!E75+'Data Input'!E77 -> 0 | C44: ='Data Input'!F75+'Data Input'!F77 -> 0 | D44: ='Data Input'!G75+'Data Input'!G77 -> 0 | E44: ='Data Input'!H75+'Data Input'!H77 -> 0 | F44: ='Data Input'!I75+'Data Input'!I77 -> 17.22 | G44: ='Data Input'!J75+'Data Input'!J77 -> 10.35 | H44: ='Data Input'!K75+'Data Input'!K77 -> 10.47 | I44: ='Data Input'!L75+'Data Input'!L77 -> 11.76
A45: (Months Purchases - General) | B45: =B44*12/('Data Input'!E143+'Data Input'!E21-'Data Input'!E142) -> #DIV/0! | C45: =C44*12/('Data Input'!F143+'Data Input'!F21-'Data Input'!F142) -> #DIV/0! | D45: =D44*12/('Data Input'!G143+'Data Input'!G21-'Data Input'!G142) -> #DIV/0! | E45: =E44*12/('Data Input'!H143+'Data Input'!H21-'Data Input'!H142) -> #DIV/0! | F45: =F44*12/('Data Input'!I143+'Data Input'!I21-'Data Input'!I142) -> 0.43674177 | G45: =G44*12/('Data Input'!J143+'Data Input'!J21-'Data Input'!J142) -> 0.32312615 | H45: =H44*12/('Data Input'!K143+'Data Input'!K21-'Data Input'!K142) -> 0.28824447 | I45: =I44*12/('Data Input'!L143+'Data Input'!L21-'Data Input'!L142) -> 0.28724963
A46: Sundary Creditors - Expenses | B46: ='Data Input'!E76 -> 0 | C46: ='Data Input'!F76 -> 0 | D46: ='Data Input'!G76 -> 0 | E46: ='Data Input'!H76 -> 0 | F46: ='Data Input'!I76 -> 0 | G46: ='Data Input'!J76 -> 0 | H46: ='Data Input'!K76 -> 0 | I46: ='Data Input'!L76 -> 0
A47: Advance from Customers | B47: ='Data Input'!E78 -> 0 | C47: ='Data Input'!F78 -> 0 | D47: ='Data Input'!G78 -> 0 | E47: ='Data Input'!H78 -> 0 | F47: ='Data Input'!I78 -> 0 | G47: ='Data Input'!J78 -> 0 | H47: ='Data Input'!K78 -> 0 | I47: ='Data Input'!L78 -> 0
A48: Provisions | B48: ='Data Input'!E80 -> 0 | C48: ='Data Input'!F80 -> 0 | D48: ='Data Input'!G80 -> 0 | E48: ='Data Input'!H80 -> 0 | F48: ='Data Input'!I80 -> 0 | G48: ='Data Input'!J80 -> 0 | H48: ='Data Input'!K80 -> 0 | I48: ='Data Input'!L80 -> 0
A49: TL Installments due within 1 year | B49: ='Data Input'!E79 -> 0 | C49: ='Data Input'!F79 -> 0 | D49: ='Data Input'!G79 -> 0 | E49: ='Data Input'!H79 -> 0 | F49: ='Data Input'!I79 -> 2.42 | G49: ='Data Input'!J79 -> 2.39 | H49: ='Data Input'!K79 -> 1.02 | I49: ='Data Input'!L79 -> 1.02
A50: Short Term Unsecured Loans | B50: ='Data Input'!E82 -> 0 | C50: ='Data Input'!F82 -> 0 | D50: ='Data Input'!G82 -> 0 | E50: ='Data Input'!H82 -> 0 | F50: ='Data Input'!I82 -> 0 | G50: ='Data Input'!J82 -> 0 | H50: ='Data Input'!K82 -> 0 | I50: ='Data Input'!L82 -> 0
A51: Other Current Liabilities | B51: ='Data Input'!E83+'Data Input'!E84+'Data Input'!E81 -> 0 | C51: ='Data Input'!F83+'Data Input'!F84+'Data Input'!F81 -> 0 | D51: ='Data Input'!G83+'Data Input'!G84+'Data Input'!G81 -> 0 | E51: ='Data Input'!H83+'Data Input'!H84+'Data Input'!H81 -> 0 | F51: ='Data Input'!I83+'Data Input'!I84+'Data Input'!I81 -> 15.31 | G51: ='Data Input'!J83+'Data Input'!J84+'Data Input'!J81 -> 12.03 | H51: ='Data Input'!K83+'Data Input'!K84+'Data Input'!K81 -> 7.56 | I51: ='Data Input'!L83+'Data Input'!L84+'Data Input'!L81 -> 8.8
A52: Total Other Current Liabilities | B52: =SUM(B46:B51)+B44 -> 0 | C52: =SUM(C46:C51)+C44 -> 0 | D52: =SUM(D46:D51)+D44 -> 0 | E52: =SUM(E46:E51)+E44 -> 0 | F52: =SUM(F46:F51)+F44 -> 34.95 | G52: =SUM(G46:G51)+G44 -> 24.77 | H52: =SUM(H46:H51)+H44 -> 19.05 | I52: =SUM(I46:I51)+I44 -> 21.58
A53: 6. Liquidity & Solvency Ratios :-
A54: NWC | B54: ='Data Input'!E139 -> 0 | C54: ='Data Input'!F139 -> 0 | D54: ='Data Input'!G139 -> 0 | E54: ='Data Input'!H139 -> 0 | F54: ='Data Input'!I139 -> 12.46 | G54: ='Data Input'!J139 -> 18.32 | H54: ='Data Input'!K139 -> 27.88 | I54: ='Data Input'!L139 -> 38.81
A55: Current ratio | B55: ='Data Input'!E140 -> #DIV/0! | C55: ='Data Input'!F140 -> #DIV/0! | D55: ='Data Input'!G140 -> #DIV/0! | E55: ='Data Input'!H140 -> #DIV/0! | F55: ='Data Input'!I140 -> 1.2303142 | G55: ='Data Input'!J140 -> 1.3090418 | H55: ='Data Input'!K140 -> 1.3130825 | I55: ='Data Input'!L140 -> 1.4237825
A56: Debt / Equity ratio | B56: ='Data Input'!E94/'Data Input'!E101 -> #DIV/0! | C56: ='Data Input'!F94/'Data Input'!F101 -> #DIV/0! | D56: ='Data Input'!G94/'Data Input'!G101 -> #DIV/0! | E56: ='Data Input'!H94/'Data Input'!H101 -> #DIV/0! | F56: ='Data Input'!I94/'Data Input'!I101 -> 0.29826353 | G56: ='Data Input'!J94/'Data Input'!J101 -> 0.20330541 | H56: ='Data Input'!K94/'Data Input'!K101 -> 0.15662181 | I56: ='Data Input'!L94/'Data Input'!L101 -> 0.11718489
A57: TOL/TNW | B57: ='Data Input'!E95/'Data Input'!E101 -> #DIV/0! | C57: ='Data Input'!F95/'Data Input'!F101 -> #DIV/0! | D57: ='Data Input'!G95/'Data Input'!G101 -> #DIV/0! | E57: ='Data Input'!H95/'Data Input'!H101 -> #DIV/0! | F57: ='Data Input'!I95/'Data Input'!I101 -> 1.6797753 | G57: ='Data Input'!J95/'Data Input'!J101 -> 1.5453928 | H57: ='Data Input'!K95/'Data Input'!K101 -> 1.893505 | I57: ='Data Input'!L95/'Data Input'!L101 -> 1.648111
A58: Debt / Equity ratio (Quasi) | B58: =('Data Input'!E94-'Data Input'!E93)/('Data Input'!E101+'Data Input'!E93) -> #DIV/0! | C58: =('Data Input'!F94-'Data Input'!F93)/('Data Input'!F101+'Data Input'!F93) -> #DIV/0! | D58: =('Data Input'!G94-'Data Input'!G93)/('Data Input'!G101+'Data Input'!G93) -> #DIV/0! | E58: =('Data Input'!H94-'Data Input'!H93)/('Data Input'!H101+'Data Input'!H93) -> #DIV/0! | F58: =('Data Input'!I94-'Data Input'!I93)/('Data Input'!I101+'Data Input'!I93) -> 0.29826353 | G58: =('Data Input'!J94-'Data Input'!J93)/('Data Input'!J101+'Data Input'!J93) -> 0.20330541 | H58: =('Data Input'!K94-'Data Input'!K93)/('Data Input'!K101+'Data Input'!K93) -> 0.15662181 | I58: =('Data Input'!L94-'Data Input'!L93)/('Data Input'!L101+'Data Input'!L93) -> 0.11718489
A59: TOL/TNW (Quasi) | B59: =('Data Input'!E95-'Data Input'!E93)/('Data Input'!E101+'Data Input'!E93) -> #DIV/0! | C59: =('Data Input'!F95-'Data Input'!F93)/('Data Input'!F101+'Data Input'!F93) -> #DIV/0! | D59: =('Data Input'!G95-'Data Input'!G93)/('Data Input'!G101+'Data Input'!G93) -> #DIV/0! | E59: =('Data Input'!H95-'Data Input'!H93)/('Data Input'!H101+'Data Input'!H93) -> #DIV/0! | F59: =('Data Input'!I95-'Data Input'!I93)/('Data Input'!I101+'Data Input'!I93) -> 1.6797753 | G59: =('Data Input'!J95-'Data Input'!J93)/('Data Input'!J101+'Data Input'!J93) -> 1.5453928 | H59: =('Data Input'!K95-'Data Input'!K93)/('Data Input'!K101+'Data Input'!K93) -> 1.893505 | I59: =('Data Input'!L95-'Data Input'!L93)/('Data Input'!L101+'Data Input'!L93) -> 1.648111
A60: 7. MPBF :-
A61: 1. Total Inventory | B61: ='Data Input'!E112 -> 0 | C61: ='Data Input'!F112 -> 0 | D61: ='Data Input'!G112 -> 0 | E61: ='Data Input'!H112 -> 0 | F61: ='Data Input'!I112 -> 36.44 | G61: ='Data Input'!J112 -> 35.11 | H61: ='Data Input'!K112 -> 57.44 | I61: ='Data Input'!L112 -> 65.42
A62: 2. Other Current Assets | B62: ='Data Input'!E122-'Data Input'!E112-'Data Input'!E109 -> 0 | C62: ='Data Input'!F122-'Data Input'!F112-'Data Input'!F109 -> 0 | D62: ='Data Input'!G122-'Data Input'!G112-'Data Input'!G109 -> 0 | E62: ='Data Input'!H122-'Data Input'!H112-'Data Input'!H109 -> 0 | F62: ='Data Input'!I122-'Data Input'!I112-'Data Input'!I109 -> 11.31 | G62: ='Data Input'!J122-'Data Input'!J112-'Data Input'!J109 -> 11.82 | H62: ='Data Input'!K122-'Data Input'!K112-'Data Input'!K109 -> 22.45 | I62: ='Data Input'!L122-'Data Input'!L112-'Data Input'!L109 -> 22.68
A63: 3. Domestic Receivables | B63: ='Data Input'!E110 -> 0 | C63: ='Data Input'!F110 -> 0 | D63: ='Data Input'!G110 -> 0 | E63: ='Data Input'!H110 -> 0 | F63: ='Data Input'!I110 -> 18.81 | G63: ='Data Input'!J110 -> 30.67 | H63: ='Data Input'!K110 -> 37.04 | I63: ='Data Input'!L110 -> 42.29
A64: 4. Export Receivables | B64: ='Data Input'!E111 -> 0 | C64: ='Data Input'!F111 -> 0 | D64: ='Data Input'!G111 -> 0 | E64: ='Data Input'!H111 -> 0 | F64: ='Data Input'!I111 -> 0 | G64: ='Data Input'!J111 -> 0 | H64: ='Data Input'!K111 -> 0 | I64: ='Data Input'!L111 -> 0
A65: 5. Total Current Assets | B65: =SUM(B61:B64) -> 0 | C65: =SUM(C61:C64) -> 0 | D65: =SUM(D61:D64) -> 0 | E65: =SUM(E61:E64) -> 0 | F65: =SUM(F61:F64) -> 66.56 | G65: =SUM(G61:G64) -> 77.6 | H65: =SUM(H61:H64) -> 116.93 | I65: =SUM(I61:I64) -> 130.39
A66: 6. Other Current Liabilities | B66: ='Data Input'!E85 -> 0 | C66: ='Data Input'!F85 -> 0 | D66: ='Data Input'!G85 -> 0 | E66: ='Data Input'!H85 -> 0 | F66: ='Data Input'!I85 -> 34.95 | G66: ='Data Input'!J85 -> 24.77 | H66: ='Data Input'!K85 -> 19.05 | I66: ='Data Input'!L85 -> 21.58
A67: 7. Working Capital Gap | B67: =+B65-B66 -> 0 | C67: =+C65-C66 -> 0 | D67: =+D65-D66 -> 0 | E67: =+E65-E66 -> 0 | F67: =+F65-F66 -> 31.61 | G67: =+G65-G66 -> 52.83 | H67: =+H65-H66 -> 97.88 | I67: =+I65-I66 -> 108.81
A68: 8. Min. Margin (25% CCA excl. Exp. Rec) | B68: =SUM(B61:B63)*25% -> 0 | C68: =SUM(C61:C63)*25% -> 0 | D68: =SUM(D61:D63)*25% -> 0 | E68: =SUM(E61:E63)*25% -> 0 | F68: =SUM(F61:F63)*25% -> 16.64 | G68: =SUM(G61:G63)*25% -> 19.4 | H68: =SUM(H61:H63)*25% -> 29.2325 | I68: =SUM(I61:I63)*25% -> 32.5975
A69: 9. Actual/ Estimated NWC | B69: ='Data Input'!E139 -> 0 | C69: ='Data Input'!F139 -> 0 | D69: ='Data Input'!G139 -> 0 | E69: ='Data Input'!H139 -> 0 | F69: ='Data Input'!I139 -> 12.46 | G69: ='Data Input'!J139 -> 18.32 | H69: ='Data Input'!K139 -> 27.88 | I69: ='Data Input'!L139 -> 38.81
A70: 10. Permissible Bank Finance (PBF) [7-8] | B70: =B67-B68 -> 0 | C70: =C67-C68 -> 0 | D70: =D67-D68 -> 0 | E70: =E67-E68 -> 0 | F70: =F67-F68 -> 14.97 | G70: =G67-G68 -> 33.43 | H70: =H67-H68 -> 68.6475 | I70: =I67-I68 -> 76.2125
A71: 11. Permissible Bank Finance (PBF) [7-9] | B71: =B67-B69 -> 0 | C71: =C67-C69 -> 0 | D71: =D67-D69 -> 0 | E71: =E67-E69 -> 0 | F71: =F67-F69 -> 19.15 | G71: =G67-G69 -> 34.51 | H71: =H67-H69 -> 70 | I71: =I67-I69 -> 70
A72: Eligible Maximum Permissible bank Finance | B72: =MIN(B70:B71) -> 0 | C72: =MIN(C70:C71) -> 0 | D72: =MIN(D70:D71) -> 0 | E72: =MIN(E70:E71) -> 0 | F72: =MIN(F70:F71) -> 14.97 | G72: =MIN(G70:G71) -> 33.43 | H72: =MIN(H70:H71) -> 68.6475 | I72: =MIN(I70:I71) -> 70
A73: Excess Bank Finance | B73: =B71-B70 -> 0 | C73: =C71-C70 -> 0 | D73: =D71-D70 -> 0 | E73: =E71-E70 -> 0 | F73: =F71-F70 -> 4.18 | G73: =G71-G70 -> 1.08 | H73: =H71-H70 -> 1.3525 | I73: =I71-I70 -> -6.2125
A74: Maximum Permissible Bank Finance | B74: =B72 -> 0 | C74: =C72 -> 0 | D74: =D72 -> 0 | E74: =E72 -> 0 | F74: =F72 -> 14.97 | G74: =G72 -> 33.43 | H74: =H72 -> 68.6475 | I74: =I72 -> 70

Sheet BSA
A1: =+'Data Input'!B5 -> Punjab National Bank
A2: =+'Data Input'!B6 -> MCC Durgapur
A3: =+'Data Input'!B7 -> Durgapur
A4: =+'Data Input'!B4 -> H R Ispat Pvt Ltd | B4: =IF('Data Input'!C10="", "", 'Data Input'!C10) -> Audited | C4: =IF('Data Input'!D10="", "", 'Data Input'!D10) -> Audited | D4: =IF('Data Input'!E10="", "", 'Data Input'!E10) -> Audited | E4: =IF('Data Input'!F10="", "", 'Data Input'!F10) -> Audited | F4: =IF('Data Input'!G10="", "", 'Data Input'!G10) -> Audited | G4: =IF('Data Input'!H10="", "", 'Data Input'!H10) -> Audited | H4: =IF('Data Input'!I10="", "", 'Data Input'!I10) -> Audited | I4: =IF('Data Input'!J10="", "", 'Data Input'!J10) -> Audited | ... K4: =IF('Data Input'!L10="", "", 'Data Input'!L10) -> Projected
B5: =IF('Data Input'!C11="", "", 'Data Input'!C11) -> 2017 | C5: =IF('Data Input'!D11="", "", 'Data Input'!D11) -> 2018 | D5: =IF('Data Input'!E11="", "", 'Data Input'!E11) -> 2019 | E5: =IF('Data Input'!F11="", "", 'Data Input'!F11) -> 2020 | F5: =IF('Data Input'!G11="", "", 'Data Input'!G11) -> 2021 | G5: =IF('Data Input'!H11="", "", 'Data Input'!H11) -> 2022 | H5: =IF('Data Input'!I11="", "", 'Data Input'!I11) -> 2023 | I5: =IF('Data Input'!J11="", "", 'Data Input'!J11) -> 2024 | ... K5: =IF('Data Input'!L11="", "", 'Data Input'!L11) -> 2026
A6: 1. ROCE CALCULATIONS :-
A7: Profit before tax | B7: ='Data Input'!C54 -> 0 | C7: ='Data Input'!D54 -> 0 | D7: ='Data Input'!E54 -> 0 | E7: ='Data Input'!F54 -> 0 | F7: ='Data Input'!G54 -> 0 | G7: ='Data Input'!H54 -> 0 | H7: ='Data Input'!I54 -> 10.58 | I7: ='Data Input'!J54 -> 7.01 | ... K7: ='Data Input'!L54 -> 12.1
A8: Add long term Interest | B8: ='Data Input'!C47 -> 0 | C8: ='Data Input'!D47 -> 0 | D8: ='Data Input'!E47 -> 0 | E8: ='Data Input'!F47 -> 0 | F8: ='Data Input'!G47 -> 0 | G8: ='Data Input'!H47 -> 0 | H8: ='Data Input'!I47 -> 0.5 | I8: ='Data Input'!J47 -> 0.6 | ... K8: ='Data Input'!L47 -> 0.12
A9: Add Extra ordinary Expenses | B9: ='Data Input'!C52 -> 0 | C9: ='Data Input'!D52 -> 0 | D9: ='Data Input'!E52 -> 0 | E9: ='Data Input'!F52 -> 0 | F9: ='Data Input'!G52 -> 0 | G9: ='Data Input'!H52 -> 0 | H9: ='Data Input'!I52 -> 0 | I9: ='Data Input'!J52 -> 0 | ... K9: ='Data Input'!L52 -> 0
A10: Less Extra ordinary income | B10: ='Data Input'!C51 -> 0 | C10: ='Data Input'!D51 -> 0 | D10: ='Data Input'!E51 -> 0 | E10: ='Data Input'!F51 -> 0 | F10: ='Data Input'!G51 -> 0 | G10: ='Data Input'!H51 -> 0 | H10: ='Data Input'!I51 -> 0.1 | I10: ='Data Input'!J51 -> 0.15 | ... K10: ='Data Input'!L51 -> 0
A11: Adjusted Op PBIT | B11: =B7+B8+B9-B10 -> 0 | C11: =C7+C8+C9-C10 -> 0 | D11: =D7+D8+D9-D10 -> 0 | E11: =E7+E8+E9-E10 -> 0 | F11: =F7+F8+F9-F10 -> 0 | G11: =G7+G8+G9-G10 -> 0 | H11: =H7+H8+H9-H10 -> 10.98 | I11: =I7+I8+I9-I10 -> 7.46 | ... K11: =K7+K8+K9-K10 -> 12.22
A12: Average Capital Employed | B12: ='Data Input'!C101+'Data Input'!C94 -> 0 | C12: ='Data Input'!D101+'Data Input'!D94 -> 0 | D12: ='Data Input'!E101+'Data Input'!E94 -> 0 | E12: ='Data Input'!F101+'Data Input'!F94 -> 0 | F12: ='Data Input'!G101+'Data Input'!G94 -> 0 | G12: ='Data Input'!H101+'Data Input'!H94 -> 0 | H12: ='Data Input'!I101+'Data Input'!I94 -> 50.84 | I12: ='Data Input'!J101+'Data Input'!J94 -> 53.15 | ... K12: ='Data Input'!L101+'Data Input'!L94 -> 66.83
A13: ROCE (%) | B13: =B11/B12 -> #DIV/0! | C13: =C11/C12 -> #DIV/0! | D13: =D11/D12 -> #DIV/0! | E13: =E11/E12 -> #DIV/0! | F13: =F11/F12 -> #DIV/0! | G13: =G11/G12 -> #DIV/0! | H13: =H11/H12 -> 0.21597168 | I13: =I11/I12 -> 0.14035748 | ... K13: =K11/K12 -> 0.18285201
A14: 2. EBIDTA :-
A15: Net profit after tax | B15: ='Data Input'!C57 -> 0 | C15: ='Data Input'!D57 -> 0 | D15: ='Data Input'!E57 -> 0 | E15: ='Data Input'!F57 -> 0 | F15: ='Data Input'!G57 -> 0 | G15: ='Data Input'!H57 -> 0 | H15: ='Data Input'!I57 -> 5.25 | I15: ='Data Input'!J57 -> 4.79 | ... K15: ='Data Input'!L57 -> 8.12
A16: Add: Tax | B16: ='Data Input'!C55+'Data Input'!C56 -> 0 | C16: ='Data Input'!D55+'Data Input'!D56 -> 0 | D16: ='Data Input'!E55+'Data Input'!E56 -> 0 | E16: ='Data Input'!F55+'Data Input'!F56 -> 0 | F16: ='Data Input'!G55+'Data Input'!G56 -> 0 | G16: ='Data Input'!H55+'Data Input'!H56 -> 0 | H16: ='Data Input'!I55+'Data Input'!I56 -> 5.33 | I16: ='Data Input'!J55+'Data Input'!J56 -> 2.22 | ... K16: ='Data Input'!L55+'Data Input'!L56 -> 3.98
A17: Add: Depreciation | B17: ='Data Input'!C29 -> 0 | C17: ='Data Input'!D29 -> 0 | D17: ='Data Input'!E29 -> 0 | E17: ='Data Input'!F29 -> 0 | F17: ='Data Input'!G29 -> 0 | G17: ='Data Input'!H29 -> 0 | H17: ='Data Input'!I29 -> 3.23 | I17: ='Data Input'!J29 -> 3.47 | ... K17: ='Data Input'!L29 -> 3.4
A18: Add: Interest | B18: ='Data Input'!C46 -> 0 | C18: ='Data Input'!D46 -> 0 | D18: ='Data Input'!E46 -> 0 | E18: ='Data Input'!F46 -> 0 | F18: ='Data Input'!G46 -> 0 | G18: ='Data Input'!H46 -> 0 | H18: ='Data Input'!I46 -> 2.45 | I18: ='Data Input'!J46 -> 3.69 | ... K18: ='Data Input'!L46 -> 4.71
A19: EBIDTA | B19: =SUM(B15:B18) -> 0 | C19: =SUM(C15:C18) -> 0 | D19: =SUM(D15:D18) -> 0 | E19: =SUM(E15:E18) -> 0 | F19: =SUM(F15:F18) -> 0 | G19: =SUM(G15:G18) -> 0 | H19: =SUM(H15:H18) -> 16.26 | I19: =SUM(I15:I18) -> 14.17 | ... K19: =SUM(K15:K18) -> 20.21
A20: PBDIT | B20: =B15+B16+B17 -> 0 | C20: =C15+C16+C17 -> 0 | D20: =D15+D16+D17 -> 0 | E20: =E15+E16+E17 -> 0 | F20: =F15+F16+F17 -> 0 | G20: =G15+G16+G17 -> 0 | H20: =H15+H16+H17 -> 13.81 | I20: =I15+I16+I17 -> 10.48 | ... K20: =K15+K16+K17 -> 15.5
A21: 3. GROWTH :-
A22: Gross Sales | B22: ='Data Input'!C12 -> 0 | C22: ='Data Input'!D12 -> 0 | D22: ='Data Input'!E12 -> 0 | E22: ='Data Input'!F12 -> 0 | F22: ='Data Input'!G12 -> 0 | G22: ='Data Input'!H12 -> 0 | H22: ='Data Input'!I12 -> 564.38 | I22: ='Data Input'!J12 -> 471.12 | ... K22: ='Data Input'!L12 -> 603.94
A23: Total Net Sales | B23: ='Data Input'!C18 -> 0 | C23: ='Data Input'!D18 -> 0 | D23: ='Data Input'!E18 -> 0 | E23: ='Data Input'!F18 -> 0 | F23: ='Data Input'!G18 -> 0 | G23: ='Data Input'!H18 -> 0 | H23: ='Data Input'!I18 -> 564.38 | I23: ='Data Input'!J18 -> 471.12 | ... K23: ='Data Input'!L18 -> 603.94
A24: Domestic Sales | B24: ='Data Input'!C13 -> 0 | C24: ='Data Input'!D13 -> 0 | D24: ='Data Input'!E13 -> 0 | E24: ='Data Input'!F13 -> 0 | F24: ='Data Input'!G13 -> 0 | G24: ='Data Input'!H13 -> 0 | H24: ='Data Input'!I13 -> 564.38 | I24: ='Data Input'!J13 -> 471.12 | ... K24: ='Data Input'!L13 -> 603.94
A25: Exports Sales | B25: ='Data Input'!C14 -> 0 | C25: ='Data Input'!D14 -> 0 | D25: ='Data Input'!E14 -> 0 | E25: ='Data Input'!F14 -> 0 | F25: ='Data Input'!G14 -> 0 | G25: ='Data Input'!H14 -> 0 | H25: ='Data Input'!I14 -> 0 | I25: ='Data Input'!J14 -> 0 | ... K25: ='Data Input'!L14 -> 0
A26: Growth in Sales (net %) | B26: - | C26: =(C23-B23)/B23 -> #DIV/0! | D26: =(D23-C23)/C23 -> #DIV/0! | E26: =(E23-D23)/D23 -> #DIV/0! | F26: =(F23-E23)/E23 -> #DIV/0! | G26: =(G23-F23)/F23 -> #DIV/0! | H26: =(H23-G23)/G23 -> #DIV/0! | I26: =(I23-H23)/H23 -> -0.16524328 | J26: =(J23-I23)/I23 -> 0.12260146 | K26: =(K23-J23)/J23 -> 0.14192255
A27: 4. Profitability :-
A28: PBT/Net sales(%) | B28: =B7/B23 -> #DIV/0! | C28: =C7/C23 -> #DIV/0! | D28: =D7/D23 -> #DIV/0! | E28: =E7/E23 -> #DIV/0! | F28: =F7/F23 -> #DIV/0! | G28: =G7/G23 -> #DIV/0! | H28: =H7/H23 -> 0.018746235 | I28: =I7/I23 -> 0.014879436 | ... K28: =K7/K23 -> 0.020035103
A29: ROCE (%) | B29: =B13 -> #DIV/0! | C29: =C13 -> #DIV/0! | D29: =D13 -> #DIV/0! | E29: =E13 -> #DIV/0! | F29: =F13 -> #DIV/0! | G29: =G13 -> #DIV/0! | H29: =H13 -> 0.21597168 | I29: =I13 -> 0.14035748 | ... K29: =K13 -> 0.18285201
A30: 5. SOLVENCY :-
A31: Paid up share capital | B31: ='Data Input'!C96 -> 0 | C31: ='Data Input'!D96 -> 0 | D31: ='Data Input'!E96 -> 0 | E31: ='Data Input'!F96 -> 0 | F31: ='Data Input'!G96 -> 0 | G31: ='Data Input'!H96 -> 0 | H31: ='Data Input'!I96 -> 5.33 | I31: ='Data Input'!J96 -> 5.33 | ... K31: ='Data Input'!L96 -> 5.33
A32: Reserves & Surplus (excluding Revaluation reserve) | B32: ='Data Input'!C97+'Data Input'!C100+'Data Input'!C98 -> 0 | C32: ='Data Input'!D97+'Data Input'!D100+'Data Input'!D98 -> 0 | D32: ='Data Input'!E97+'Data Input'!E100+'Data Input'!E98 -> 0 | E32: ='Data Input'!F97+'Data Input'!F100+'Data Input'!F98 -> 0 | F32: ='Data Input'!G97+'Data Input'!G100+'Data Input'!G98 -> 0 | G32: ='Data Input'!H97+'Data Input'!H100+'Data Input'!H98 -> 0 | H32: ='Data Input'!I97+'Data Input'!I100+'Data Input'!I98 -> 31.83 | I32: ='Data Input'!J97+'Data Input'!J100+'Data Input'!J98 -> 36.62 | ... K32: ='Data Input'!L97+'Data Input'!L100+'Data Input'!L98 -> 51.58
A33: Accumulated losses & Intangible assets | B33: ='Data Input'!C136 -> 0 | C33: ='Data Input'!D136 -> 0 | D33: ='Data Input'!E136 -> 0 | E33: ='Data Input'!F136 -> 0 | F33: ='Data Input'!G136 -> 0 | G33: ='Data Input'!H136 -> 0 | H33: ='Data Input'!I136 -> 0 | I33: ='Data Input'!J136 -> 0 | ... K33: ='Data Input'!L136 -> 0
A34: Investments outside business | B34: ='Data Input'!C130 -> 0 | C34: ='Data Input'!D130 -> 0 | D34: ='Data Input'!E130 -> 0 | E34: ='Data Input'!F130 -> 0 | F34: ='Data Input'!G130 -> 0 | G34: ='Data Input'!H130 -> 0 | H34: ='Data Input'!I130 -> 0 | I34: ='Data Input'!J130 -> 0 | ... K34: ='Data Input'!L130 -> 0
A35: Investment in Associate Concern | B35: ='Data Input'!C131 -> 0 | C35: ='Data Input'!D131 -> 0 | D35: ='Data Input'!E131 -> 0 | E35: ='Data Input'!F131 -> 0 | F35: ='Data Input'!G131 -> 0 | G35: ='Data Input'!H131 -> 0 | H35: ='Data Input'!I131 -> 0 | I35: ='Data Input'!J131 -> 0 | ... K35: ='Data Input'!L131 -> 0
A36: Deffered tax liability (Asset) | B36: =+'Data Input'!C99 -> 0 | C36: =+'Data Input'!D99 -> 0 | D36: =+'Data Input'!E99 -> 0 | E36: =+'Data Input'!F99 -> 0 | F36: =+'Data Input'!G99 -> 0 | G36: =+'Data Input'!H99 -> 0 | H36: =+'Data Input'!I99 -> 2 | I36: =+'Data Input'!J99 -> 2.22 | ... K36: =+'Data Input'!L99 -> 2.91
A37: Net Owned Funds | B37: =B31+B32-B33-B34-B35+B36 -> 0 | C37: =C31+C32-C33-C34-C35+C36 -> 0 | D37: =D31+D32-D33-D34-D35+D36 -> 0 | E37: =E31+E32-E33-E34-E35+E36 -> 0 | F37: =F31+F32-F33-F34-F35+F36 -> 0 | G37: =G31+G32-G33-G34-G35+G36 -> 0 | H37: =H31+H32-H33-H34-H35+H36 -> 39.16 | I37: =I31+I32-I33-I34-I35+I36 -> 44.17 | ... K37: =K31+K32-K33-K34-K35+K36 -> 59.82
A38: Tangible Net Worth | B38: =B31+B32+B36-B33 -> 0 | C38: =C31+C32+C36-C33 -> 0 | D38: =D31+D32+D36-D33 -> 0 | E38: =E31+E32+E36-E33 -> 0 | F38: =F31+F32+F36-F33 -> 0 | G38: =G31+G32+G36-G33 -> 0 | H38: =H31+H32+H36-H33 -> 39.16 | I38: =I31+I32+I36-I33 -> 44.17 | ... K38: =K31+K32+K36-K33 -> 59.82
A39: Debt / Equity ratio | B39: ='Data Input'!C94/B38 -> #DIV/0! | C39: ='Data Input'!D94/C38 -> #DIV/0! | D39: ='Data Input'!E94/D38 -> #DIV/0! | E39: ='Data Input'!F94/E38 -> #DIV/0! | F39: ='Data Input'!G94/F38 -> #DIV/0! | G39: ='Data Input'!H94/G38 -> #DIV/0! | H39: ='Data Input'!I94/H38 -> 0.29826353 | I39: ='Data Input'!J94/I38 -> 0.20330541 | ... K39: ='Data Input'!L94/K38 -> 0.11718489
A40: TOL/TNW | B40: ='Data Input'!C95/BSA!B38 -> #DIV/0! | C40: ='Data Input'!D95/BSA!C38 -> #DIV/0! | D40: ='Data Input'!E95/BSA!D38 -> #DIV/0! | E40: ='Data Input'!F95/BSA!E38 -> #DIV/0! | F40: ='Data Input'!G95/BSA!F38 -> #DIV/0! | G40: ='Data Input'!H95/BSA!G38 -> #DIV/0! | H40: ='Data Input'!I95/BSA!H38 -> 1.6797753 | I40: ='Data Input'!J95/BSA!I38 -> 1.5453928 | ... K40: ='Data Input'!L95/BSA!K38 -> 1.648111
A41: Debt / Equity ratio (Quasi) | B41: =('Data Input'!C94-'Data Input'!C93)/(BSA!B38-'Data Input'!C93) -> #DIV/0! | C41: =('Data Input'!D94-'Data Input'!D93)/(BSA!C38-'Data Input'!D93) -> #DIV/0! | D41: =('Data Input'!E94-'Data Input'!E93)/(BSA!D38-'Data Input'!E93) -> #DIV/0! | E41: =('Data Input'!F94-'Data Input'!F93)/(BSA!E38-'Data Input'!F93) -> #DIV/0! | F41: =('Data Input'!G94-'Data Input'!G93)/(BSA!F38-'Data Input'!G93) -> #DIV/0! | G41: =('Data Input'!H94-'Data Input'!H93)/(BSA!G38-'Data Input'!H93) -> #DIV/0! | H41: =('Data Input'!I94-'Data Input'!I93)/(BSA!H38-'Data Input'!I93) -> 0.29826353 | I41: =('Data Input'!J94-'Data Input'!J93)/(BSA!I38-'Data Input'!J93) -> 0.20330541 | ... K41: =('Data Input'!L94-'Data Input'!L93)/(BSA!K38-'Data Input'!L93) -> 0.11718489
A42: TOL/TNW (Quasi) | B42: =('Data Input'!C95-'Data Input'!C93)/(BSA!B38-'Data Input'!C93) -> #DIV/0! | C42: =('Data Input'!D95-'Data Input'!D93)/(BSA!C38-'Data Input'!D93) -> #DIV/0! | D42: =('Data Input'!E95-'Data Input'!E93)/(BSA!D38-'Data Input'!E93) -> #DIV/0! | E42: =('Data Input'!F95-'Data Input'!F93)/(BSA!E38-'Data Input'!F93) -> #DIV/0! | F42: =('Data Input'!G95-'Data Input'!G93)/(BSA!F38-'Data Input'!G93) -> #DIV/0! | G42: =('Data Input'!H95-'Data Input'!H93)/(BSA!G38-'Data Input'!H93) -> #DIV/0! | H42: =('Data Input'!I95-'Data Input'!I93)/(BSA!H38-'Data Input'!I93) -> 1.6797753 | I42: =('Data Input'!J95-'Data Input'!J93)/(BSA!I38-'Data Input'!J93) -> 1.5453928 | ... K42: =('Data Input'!L95-'Data Input'!L93)/(BSA!K38-'Data Input'!L93) -> 1.648111
A43: 6. LIQUIDITY : -
A44: NWC | B44: ='Data Input'!C122-'Data Input'!C86 -> 0 | C44: ='Data Input'!D122-'Data Input'!D86 -> 0 | D44: ='Data Input'!E122-'Data Input'!E86 -> 0 | E44: ='Data Input'!F122-'Data Input'!F86 -> 0 | F44: ='Data Input'!G122-'Data Input'!G86 -> 0 | G44: ='Data Input'!H122-'Data Input'!H86 -> 0 | H44: ='Data Input'!I122-'Data Input'!I86 -> 12.46 | I44: ='Data Input'!J122-'Data Input'!J86 -> 18.32 | ... K44: ='Data Input'!L122-'Data Input'!L86 -> 38.81
A45: Current ratio | B45: ='Data Input'!C122/'Data Input'!C86 -> #DIV/0! | C45: ='Data Input'!D122/'Data Input'!D86 -> #DIV/0! | D45: ='Data Input'!E122/'Data Input'!E86 -> #DIV/0! | E45: ='Data Input'!F122/'Data Input'!F86 -> #DIV/0! | F45: ='Data Input'!G122/'Data Input'!G86 -> #DIV/0! | G45: ='Data Input'!H122/'Data Input'!H86 -> #DIV/0! | H45: ='Data Input'!I122/'Data Input'!I86 -> 1.2303142 | I45: ='Data Input'!J122/'Data Input'!J86 -> 1.3090418 | ... K45: ='Data Input'!L122/'Data Input'!L86 -> 1.4237825
A46: DSCR | B46: =(BSA!B15+BSA!B8+BSA!B17)/('Data Input'!C79+BSA!B8) -> #DIV/0! | C46: =(BSA!C15+BSA!C8+BSA!C17)/('Data Input'!D79+BSA!C8) -> #DIV/0! | D46: =(BSA!D15+BSA!D8+BSA!D17)/('Data Input'!E79+BSA!D8) -> #DIV/0! | E46: =(BSA!E15+BSA!E8+BSA!E17)/('Data Input'!F79+BSA!E8) -> #DIV/0! | F46: =(BSA!F15+BSA!F8+BSA!F17)/('Data Input'!G79+BSA!F8) -> #DIV/0! | G46: =(BSA!G15+BSA!G8+BSA!G17)/('Data Input'!H79+BSA!G8) -> #DIV/0! | H46: =(BSA!H15+BSA!H8+BSA!H17)/('Data Input'!I79+BSA!H8) -> 3.0753425 | I46: =(BSA!I15+BSA!I8+BSA!I17)/('Data Input'!J79+BSA!I8) -> 2.9632107 | ... K46: =(BSA!K15+BSA!K8+BSA!K17)/('Data Input'!L79+BSA!K8) -> 10.210526
A47: 7. EFFICIENCY :-
A48: Capital turnover (sales /capital employed) | B48: =+B22/'Data Input'!C101 -> #DIV/0! | C48: =+C22/'Data Input'!D101 -> #DIV/0! | D48: =+D22/'Data Input'!E101 -> #DIV/0! | E48: =+E22/'Data Input'!F101 -> #DIV/0! | F48: =+F22/'Data Input'!G101 -> #DIV/0! | G48: =+G22/'Data Input'!H101 -> #DIV/0! | H48: =+H22/'Data Input'!I101 -> 14.412155 | I48: =+I22/'Data Input'!J101 -> 10.666063 | ... K48: =+K22/'Data Input'!L101 -> 10.095955
A49: Funding Turnover (Sales/ Long Term Funds) | B49: =+B22/('Data Input'!C101+'Data Input'!C94) -> #DIV/0! | C49: =+C22/('Data Input'!D101+'Data Input'!D94) -> #DIV/0! | D49: =+D22/('Data Input'!E101+'Data Input'!E94) -> #DIV/0! | E49: =+E22/('Data Input'!F101+'Data Input'!F94) -> #DIV/0! | F49: =+F22/('Data Input'!G101+'Data Input'!G94) -> #DIV/0! | G49: =+G22/('Data Input'!H101+'Data Input'!H94) -> #DIV/0! | H49: =+H22/('Data Input'!I101+'Data Input'!I94) -> 11.101101 | I49: =+I22/('Data Input'!J101+'Data Input'!J94) -> 8.8639699 | ... K49: =+K22/('Data Input'!L101+'Data Input'!L94) -> 9.0369594
A50: Asset Turnover (Sales/ Total Assets) | B50: =+B22/'Data Input'!C137 -> #DIV/0! | C50: =+C22/'Data Input'!D137 -> #DIV/0! | D50: =+D22/'Data Input'!E137 -> #DIV/0! | E50: =+E22/'Data Input'!F137 -> #DIV/0! | F50: =+F22/'Data Input'!G137 -> #DIV/0! | G50: =+G22/'Data Input'!H137 -> #DIV/0! | H50: =+H22/'Data Input'!I137 -> 5.3781208 | I50: =+I22/'Data Input'!J137 -> 4.1903407 | ... K50: =+K22/'Data Input'!L137 -> 3.8125118
A51: 8. WORKING CAPITAL MANAGEMENT:-
A52: NWC/TCA (%) | B52: =+B44/'Data Input'!C122 -> #DIV/0! | C52: =+C44/'Data Input'!D122 -> #DIV/0! | D52: =+D44/'Data Input'!E122 -> #DIV/0! | E52: =+E44/'Data Input'!F122 -> #DIV/0! | F52: =+F44/'Data Input'!G122 -> #DIV/0! | G52: =+G44/'Data Input'!H122 -> #DIV/0! | H52: =+H44/'Data Input'!I122 -> 0.18719952 | I52: =+I44/'Data Input'!J122 -> 0.23608247 | ... K52: =+K44/'Data Input'!L122 -> 0.29764552
A53: Inventory turnover ratio | B53: =+'Data Input'!C112/BSA!B22 -> #DIV/0! | C53: =+'Data Input'!D112/BSA!C22 -> #DIV/0! | D53: =+'Data Input'!E112/BSA!D22 -> #DIV/0! | E53: =+'Data Input'!F112/BSA!E22 -> #DIV/0! | F53: =+'Data Input'!G112/BSA!F22 -> #DIV/0! | G53: =+'Data Input'!H112/BSA!G22 -> #DIV/0! | H53: =+'Data Input'!I112/BSA!H22 -> 0.064566427 | I53: =+'Data Input'!J112/BSA!I22 -> 0.074524537 | ... K53: =+'Data Input'!L112/BSA!K22 -> 0.10832202
A54: Debtors turnover ratio | B54: ='Data Input'!C109+'Data Input'!C129/B22 -> #DIV/0! | C54: ='Data Input'!D109+'Data Input'!D129/C22 -> #DIV/0! | D54: ='Data Input'!E109+'Data Input'!E129/D22 -> #DIV/0! | E54: ='Data Input'!F109+'Data Input'!F129/E22 -> #DIV/0! | F54: ='Data Input'!G109+'Data Input'!G129/F22 -> #DIV/0! | G54: ='Data Input'!H109+'Data Input'!H129/G22 -> #DIV/0! | H54: ='Data Input'!I109+'Data Input'!I129/H22 -> 18.81 | I54: ='Data Input'!J109+'Data Input'!J129/I22 -> 30.67 | ... K54: ='Data Input'!L109+'Data Input'!L129/K22 -> 42.29
A55: Creditors turnover ratio | B55: ='Data Input'!C75+'Data Input'!C76+'Data Input'!C77/B22 -> #DIV/0! | C55: ='Data Input'!D75+'Data Input'!D76/C22 -> #DIV/0! | D55: ='Data Input'!E75+'Data Input'!E76/D22 -> #DIV/0! | E55: ='Data Input'!F75+'Data Input'!F76/E22 -> #DIV/0! | F55: ='Data Input'!G75+'Data Input'!G76/F22 -> #DIV/0! | G55: ='Data Input'!H75+'Data Input'!H76/G22 -> #DIV/0! | H55: ='Data Input'!I75+'Data Input'!I76/H22 -> 17.22 | I55: ='Data Input'!J75+'Data Input'!J76/I22 -> 10.35 | J55: ='Data Input'!K75+'Data Input'!K76/J22 -> 10.47 | K55: ='Data Input'!L75+'Data Input'!L76/K22 -> 11.76
A56: STB/Net Sales (%) | B56: =+'Data Input'!C74/B22 -> #DIV/0! | C56: =+'Data Input'!D74/C22 -> #DIV/0! | D56: =+'Data Input'!E74/D22 -> #DIV/0! | E56: =+'Data Input'!F74/E22 -> #DIV/0! | F56: =+'Data Input'!G74/F22 -> #DIV/0! | G56: =+'Data Input'!H74/G22 -> #DIV/0! | H56: =+'Data Input'!I74/H22 -> 0.033931039 | I56: =+'Data Input'!J74/I22 -> 0.073250976 | ... K56: =+'Data Input'!L74/K22 -> 0.11590555
A57: 9. Build Up of NWC :-
A58: Opening Net Working Capital | B58: NA | C58: =+B66 -> 0 | D58: =+C66 -> 0 | E58: =+D66 -> 0 | F58: =+E66 -> 0 | G58: =+F66 -> 0 | H58: =+G66 -> 0 | I58: =+H66 -> 12.46 | J58: =+I66 -> 18.32 | K58: =+J66 -> 27.88
A59: Increase in Net Worth | B59: NA | C59: ='Data Input'!D101-'Data Input'!C101 -> 0 | D59: ='Data Input'!E101-'Data Input'!D101 -> 0 | E59: ='Data Input'!F101-'Data Input'!E101 -> 0 | F59: ='Data Input'!G101-'Data Input'!F101 -> 0 | G59: ='Data Input'!H101-'Data Input'!G101 -> 0 | H59: ='Data Input'!I101-'Data Input'!H101 -> 39.16 | I59: ='Data Input'!J101-'Data Input'!I101 -> 5.01 | J59: ='Data Input'!K101-'Data Input'!J101 -> 7.1 | K59: ='Data Input'!L101-'Data Input'!K101 -> 8.55
A60: Increase in Term Liabilities | B60: NA | C60: ='Data Input'!D94-'Data Input'!C94 -> 0 | D60: ='Data Input'!E94-'Data Input'!D94 -> 0 | E60: ='Data Input'!F94-'Data Input'!E94 -> 0 | F60: ='Data Input'!G94-'Data Input'!F94 -> 0 | G60: ='Data Input'!H94-'Data Input'!G94 -> 0 | H60: ='Data Input'!I94-'Data Input'!H94 -> 11.68 | I60: ='Data Input'!J94-'Data Input'!I94 -> -2.7 | J60: ='Data Input'!K94-'Data Input'!J94 -> -0.95 | K60: ='Data Input'!L94-'Data Input'!K94 -> -1.02
A61: Sub Total | B61: NA | C61: =+C58+C59+C60 -> 0 | D61: =+D58+D59+D60 -> 0 | E61: =+E58+E59+E60 -> 0 | F61: =+F58+F59+F60 -> 0 | G61: =+G58+G59+G60 -> 0 | H61: =+H58+H59+H60 -> 50.84 | I61: =+I58+I59+I60 -> 14.77 | J61: =+J58+J59+J60 -> 24.47 | K61: =+K58+K59+K60 -> 35.41
A62: LESS: Increase/ (Decrease) in Net Block | B62: NA | C62: ='Data Input'!D126-'Data Input'!C126 -> 0 | D62: ='Data Input'!E126-'Data Input'!D126 -> 0 | E62: ='Data Input'!F126-'Data Input'!E126 -> 0 | F62: ='Data Input'!G126-'Data Input'!F126 -> 0 | G62: ='Data Input'!H126-'Data Input'!G126 -> 0 | H62: ='Data Input'!I126-'Data Input'!H126 -> 34.29 | I62: ='Data Input'!J126-'Data Input'!I126 -> 0.5 | J62: ='Data Input'!K126-'Data Input'!J126 -> -3.4 | K62: ='Data Input'!L126-'Data Input'!K126 -> -3.4
A63: Increase in Non Current Assets | B63: NA | C63: ='Data Input'!D135-'Data Input'!C135 -> 0 | D63: ='Data Input'!E135-'Data Input'!D135 -> 0 | E63: ='Data Input'!F135-'Data Input'!E135 -> 0 | F63: ='Data Input'!G135-'Data Input'!F135 -> 0 | G63: ='Data Input'!H135-'Data Input'!G135 -> 0 | H63: ='Data Input'!I135-'Data Input'!H135 -> 4.09 | I63: ='Data Input'!J135-'Data Input'!I135 -> -4.05 | J63: ='Data Input'!K135-'Data Input'!J135 -> -0.01 | K63: ='Data Input'!L135-'Data Input'!K135 -> 0
A64: Increase in intangible Assets | B64: NA | C64: ='Data Input'!D136-'Data Input'!C136 -> 0 | D64: ='Data Input'!E136-'Data Input'!D136 -> 0 | E64: ='Data Input'!F136-'Data Input'!E136 -> 0 | F64: ='Data Input'!G136-'Data Input'!F136 -> 0 | G64: ='Data Input'!H136-'Data Input'!G136 -> 0 | H64: ='Data Input'!I136-'Data Input'!H136 -> 0 | I64: ='Data Input'!J136-'Data Input'!I136 -> 0 | J64: ='Data Input'!K136-'Data Input'!J136 -> 0 | K64: ='Data Input'!L136-'Data Input'!K136 -> 0
A65: Sub Total | B65: NA | C65: =SUM(C62:C64) -> 0 | D65: =SUM(D62:D64) -> 0 | E65: =SUM(E62:E64) -> 0 | F65: =SUM(F62:F64) -> 0 | G65: =SUM(G62:G64) -> 0 | H65: =SUM(H62:H64) -> 38.38 | I65: =SUM(I62:I64) -> -3.55 | J65: =SUM(J62:J64) -> -3.41 | K65: =SUM(K62:K64) -> -3.4
A66: Net Working Capital | B66: =+B44 -> 0 | C66: =+C61-C65 -> 0 | D66: =+D61-D65 -> 0 | E66: =+E61-E65 -> 0 | F66: =+F61-F65 -> 0 | G66: =+G61-G65 -> 0 | H66: =+H61-H65 -> 12.46 | I66: =+I61-I65 -> 18.32 | J66: =+J61-J65 -> 27.88 | K66: =+K61-K65 -> 38.81
A67: 10. Build up of TNW :-
A68: Opening TNW | B68: NA | C68: =+B71 -> 0 | D68: =+C71 -> 0 | E68: =+D71 -> 0 | F68: =+E71 -> 0 | G68: =+F71 -> 0 | H68: =+G71 -> 0 | I68: =+H71 -> 39.16 | J68: =+I71 -> 44.17 | K68: =+J71 -> 51.27
A69: ADD: Profit & Infusiuon of Capital | B69: NA | C69: ='Data Input'!D101-'Data Input'!C101 -> 0 | D69: ='Data Input'!E101-'Data Input'!D101 -> 0 | E69: ='Data Input'!F101-'Data Input'!E101 -> 0 | F69: ='Data Input'!G101-'Data Input'!F101 -> 0 | G69: ='Data Input'!H101-'Data Input'!G101 -> 0 | H69: ='Data Input'!I101-'Data Input'!H101 -> 39.16 | I69: ='Data Input'!J101-'Data Input'!I101 -> 5.01 | J69: ='Data Input'!K101-'Data Input'!J101 -> 7.1 | K69: ='Data Input'!L101-'Data Input'!K101 -> 8.55
A70: Less: Losses and increase in other investments | B70: NA | C70: =+C68+C69-C71 -> 0 | D70: =+D68+D69-D71 -> 0 | E70: =+E68+E69-E71 -> 0 | F70: =+F68+F69-F71 -> 0 | G70: =+G68+G69-G71 -> 0 | H70: =+H68+H69-H71 -> 0 | I70: =+I68+I69-I71 -> 0 | J70: =+J68+J69-J71 -> 0 | K70: =+K68+K69-K71 -> 0
A71: Closing TNW | B71: =+B38 -> 0 | C71: =+C38 -> 0 | D71: =+D38 -> 0 | E71: =+E38 -> 0 | F71: =+F38 -> 0 | G71: =+G38 -> 0 | H71: =+H38 -> 39.16 | I71: =+I38 -> 44.17 | ... K71: =+K38 -> 59.82

Sheet 7A
A1: =+'Data Input'!B5 -> Punjab National Bank
A2: =+'Data Input'!B6 -> MCC Durgapur
A3: =+'Data Input'!B7 -> Durgapur
A4: =+'Data Input'!B4 -> H R Ispat Pvt Ltd | B4: =IF('Data Input'!E10="", "", 'Data Input'!E10) -> Audited | C4: =IF('Data Input'!F10="", "", 'Data Input'!F10) -> Audited | D4: =IF('Data Input'!G10="", "", 'Data Input'!G10) -> Audited | E4: =IF('Data Input'!H10="", "", 'Data Input'!H10) -> Audited | F4: =IF('Data Input'!I10="", "", 'Data Input'!I10) -> Audited | G4: =IF('Data Input'!J10="", "", 'Data Input'!J10) -> Audited | H4: =IF('Data Input'!K10="", "", 'Data Input'!K10) -> Projected | I4: =IF('Data Input'!L10="", "", 'Data Input'!L10) -> Projected
B5: =IF('Data Input'!E11="", "", 'Data Input'!E11) -> 2019 | C5: =IF('Data Input'!F11="", "", 'Data Input'!F11) -> 2020 | D5: =IF('Data Input'!G11="", "", 'Data Input'!G11) -> 2021 | E5: =IF('Data Input'!H11="", "", 'Data Input'!H11) -> 2022 | F5: =IF('Data Input'!I11="", "", 'Data Input'!I11) -> 2023 | G5: =IF('Data Input'!J11="", "", 'Data Input'!J11) -> 2024 | H5: =IF('Data Input'!K11="", "", 'Data Input'!K11) -> 2025 | I5: =IF('Data Input'!L11="", "", 'Data Input'!L11) -> 2026
A6: Gross Sales | B6: =+BSA!D22 -> 0 | C6: =+BSA!E22 -> 0 | D6: =+BSA!F22 -> 0 | E6: =+BSA!G22 -> 0 | F6: =+BSA!H22 -> 564.38 | G6: =+BSA!I22 -> 471.12 | H6: =+BSA!J22 -> 528.88 | I6: =+BSA!K22 -> 603.94
A7: - Domestic | B7: =+BSA!D24 -> 0 | C7: =+BSA!E24 -> 0 | D7: =+BSA!F24 -> 0 | E7: =+BSA!G24 -> 0 | F7: =+BSA!H24 -> 564.38 | G7: =+BSA!I24 -> 471.12 | H7: =+BSA!J24 -> 528.88 | I7: =+BSA!K24 -> 603.94
A8: - Export | B8: =+BSA!D25 -> 0 | C8: =+BSA!E25 -> 0 | D8: =+BSA!F25 -> 0 | E8: =+BSA!G25 -> 0 | F8: =+BSA!H25 -> 0 | G8: =+BSA!I25 -> 0 | H8: =+BSA!J25 -> 0 | I8: =+BSA!K25 -> 0
A9: % growth | B9: =+BSA!D26 -> #DIV/0! | C9: =+BSA!E26 -> #DIV/0! | D9: =+BSA!F26 -> #DIV/0! | E9: =+BSA!G26 -> #DIV/0! | F9: =+BSA!H26 -> #DIV/0! | G9: =+BSA!I26 -> -0.16524328 | H9: =+BSA!J26 -> 0.12260146 | I9: =+BSA!K26 -> 0.14192255
A10: Net Sales | B10: =+BSA!D23-B13 -> 0 | C10: =+BSA!E23-C13 -> 0 | D10: =+BSA!F23-D13 -> 0 | E10: =+BSA!G23-E13 -> 0 | F10: =+BSA!H23-F13 -> 564.38 | G10: =+BSA!I23-G13 -> 471.12 | H10: =+BSA!J23-H13 -> 528.88 | I10: =+BSA!K23-I13 -> 603.94
A11: Raw material consumed | B11: ='Data Input'!E23 -> 0 | C11: ='Data Input'!F23 -> 0 | D11: ='Data Input'!G23 -> 0 | E11: ='Data Input'!H23 -> 0 | F11: ='Data Input'!I23 -> 473.14 | G11: ='Data Input'!J23 -> 384.37 | H11: ='Data Input'!K23 -> 435.88 | I11: ='Data Input'!L23 -> 491.28
A12: Purchase of Stock-In trade for Resale | B12: ='Data Input'!E24 -> 0 | C12: ='Data Input'!F24 -> 0 | D12: ='Data Input'!G24 -> 0 | E12: ='Data Input'!H24 -> 0 | F12: ='Data Input'!I24 -> 11.37 | G12: ='Data Input'!J24 -> 8.3 | H12: ='Data Input'!K24 -> 9.81 | I12: ='Data Input'!L24 -> 11.05
A13: Other Operating Income | B13: ='Data Input'!E15 -> 0 | C13: ='Data Input'!F15 -> 0 | D13: ='Data Input'!G15 -> 0 | E13: ='Data Input'!H15 -> 0 | F13: ='Data Input'!I15 -> 0 | G13: ='Data Input'!J15 -> 0 | H13: ='Data Input'!K15 -> 0 | I13: ='Data Input'!L15 -> 0 | J13: =+F13+F14 -> 0.1 | K13: =+G13+G14 -> 0.15
A14: Other Non operating Income | B14: ='Data Input'!E51 -> 0 | C14: ='Data Input'!F51 -> 0 | D14: ='Data Input'!G51 -> 0 | E14: ='Data Input'!H51 -> 0 | F14: ='Data Input'!I51 -> 0.1 | G14: ='Data Input'!J51 -> 0.15 | H14: ='Data Input'!K51 -> 0 | I14: ='Data Input'!L51 -> 0
A15: Operating Profit/Loss | B15: ='Data Input'!E50 -> 0 | C15: ='Data Input'!F50 -> 0 | D15: ='Data Input'!G50 -> 0 | E15: ='Data Input'!H50 -> 0 | F15: ='Data Input'!I50 -> 10.48 | G15: ='Data Input'!J50 -> 6.86 | H15: ='Data Input'!K50 -> 9.46 | I15: ='Data Input'!L50 -> 11.88
A16: Profit before tax | B16: ='Data Input'!E54 -> 0 | C16: ='Data Input'!F54 -> 0 | D16: ='Data Input'!G54 -> 0 | E16: ='Data Input'!H54 -> 0 | F16: ='Data Input'!I54 -> 10.58 | G16: ='Data Input'!J54 -> 7.01 | H16: ='Data Input'!K54 -> 9.66 | I16: ='Data Input'!L54 -> 12.1
A17: Profit after tax | B17: ='Data Input'!E57 -> 0 | C17: ='Data Input'!F57 -> 0 | D17: ='Data Input'!G57 -> 0 | E17: ='Data Input'!H57 -> 0 | F17: ='Data Input'!I57 -> 5.25 | G17: ='Data Input'!J57 -> 4.79 | H17: ='Data Input'!K57 -> 6.84 | I17: ='Data Input'!L57 -> 8.12
A18: Depreciation / Amortization of expenses | B18: ='Data Input'!E29 -> 0 | C18: ='Data Input'!F29 -> 0 | D18: ='Data Input'!G29 -> 0 | E18: ='Data Input'!H29 -> 0 | F18: ='Data Input'!I29 -> 3.23 | G18: ='Data Input'!J29 -> 3.47 | H18: ='Data Input'!K29 -> 3.4 | I18: ='Data Input'!L29 -> 3.4
A19: Cash profit | B19: ='Data Input'!E57+'Data Input'!E29+'Data Input'!E56 -> 0 | C19: ='Data Input'!F57+'Data Input'!F29+'Data Input'!F56 -> 0 | D19: ='Data Input'!G57+'Data Input'!G29+'Data Input'!G56 -> 0 | E19: ='Data Input'!H57+'Data Input'!H29+'Data Input'!H56 -> 0 | F19: ='Data Input'!I57+'Data Input'!I29+'Data Input'!I56 -> 8.48 | G19: ='Data Input'!J57+'Data Input'!J29+'Data Input'!J56 -> 8.26 | H19: ='Data Input'!K57+'Data Input'!K29+'Data Input'!K56 -> 10.24 | I19: ='Data Input'!L57+'Data Input'!L29+'Data Input'!L56 -> 11.52
A20: EBIDTA / PBIDTA | B20: =BSA!D19 -> 0 | C20: =BSA!E19 -> 0 | D20: =BSA!F19 -> 0 | E20: =BSA!G19 -> 0 | F20: =BSA!H19 -> 16.26 | G20: =BSA!I19 -> 14.17 | H20: =BSA!J19 -> 17.86 | I20: =BSA!K19 -> 20.21
A21: Paid up capital | B21: ='Data Input'!E96 -> 0 | C21: ='Data Input'!F96 -> 0 | D21: ='Data Input'!G96 -> 0 | E21: ='Data Input'!H96 -> 0 | F21: ='Data Input'!I96 -> 5.33 | G21: ='Data Input'!J96 -> 5.33 | H21: ='Data Input'!K96 -> 5.33 | I21: ='Data Input'!L96 -> 5.33
A22: Reserves and Surplus / Other equity excluding revaluation reserves | B22: ='Data Input'!E97+'Data Input'!E100+'Data Input'!E98 -> 0 | C22: ='Data Input'!F97+'Data Input'!F100+'Data Input'!F98 -> 0 | D22: ='Data Input'!G97+'Data Input'!G100+'Data Input'!G98 -> 0 | E22: ='Data Input'!H97+'Data Input'!H100+'Data Input'!H98 -> 0 | F22: ='Data Input'!I97+'Data Input'!I100+'Data Input'!I98 -> 31.83 | G22: ='Data Input'!J97+'Data Input'!J100+'Data Input'!J98 -> 36.62 | H22: ='Data Input'!K97+'Data Input'!K100+'Data Input'!K98 -> 43.46 | I22: ='Data Input'!L97+'Data Input'!L100+'Data Input'!L98 -> 51.58
A23: Intangible Assets / Misc assets not witten off | B23: ='Data Input'!E136 -> 0 | C23: ='Data Input'!F136 -> 0 | D23: ='Data Input'!G136 -> 0 | E23: ='Data Input'!H136 -> 0 | F23: ='Data Input'!I136 -> 0 | G23: ='Data Input'!J136 -> 0 | H23: ='Data Input'!K136 -> 0 | I23: ='Data Input'!L136 -> 0
A24: Accumulated losses | B24: 0 | C24: 0 | D24: 0 | E24: 0 | F24: 0 | G24: 0 | H24: 0 | I24: 0
A25: Deferred Tax Liability/Asset | B25: ='Data Input'!E99 -> 0 | C25: ='Data Input'!F99 -> 0 | D25: ='Data Input'!G99 -> 0 | E25: ='Data Input'!H99 -> 0 | F25: ='Data Input'!I99 -> 2 | G25: ='Data Input'!J99 -> 2.22 | H25: ='Data Input'!K99 -> 2.48 | I25: ='Data Input'!L99 -> 2.91
A26: a) Tangible Net Worth | B26: ='Data Input'!E101 -> 0 | C26: ='Data Input'!F101 -> 0 | D26: ='Data Input'!G101 -> 0 | E26: ='Data Input'!H101 -> 0 | F26: ='Data Input'!I101 -> 39.16 | G26: ='Data Input'!J101 -> 44.17 | H26: ='Data Input'!K101 -> 51.27 | I26: ='Data Input'!L101 -> 59.82
A27: b) Investment in allied concerns and amount of cross holdings | B27: ='Data Input'!E130 -> 0 | C27: ='Data Input'!F130 -> 0 | D27: ='Data Input'!G130 -> 0 | E27: ='Data Input'!H130 -> 0 | F27: ='Data Input'!I130 -> 0 | G27: ='Data Input'!J130 -> 0 | H27: ='Data Input'!K130 -> 0 | I27: ='Data Input'!L130 -> 0
A28: c) Net owned funds (a –b) | B28: =B26-B27 -> 0 | C28: =C26-C27 -> 0 | D28: =D26-D27 -> 0 | E28: =E26-E27 -> 0 | F28: =F26-F27 -> 39.16 | G28: =G26-G27 -> 44.17 | H28: =H26-H27 -> 51.27 | I28: =I26-I27 -> 59.82
A29: Loan to allied / asscoiate concern | B29: ='Data Input'!E132 -> 0 | C29: ='Data Input'!F132 -> 0 | D29: ='Data Input'!G132 -> 0 | E29: ='Data Input'!H132 -> 0 | F29: ='Data Input'!I132 -> 0 | G29: ='Data Input'!J132 -> 0 | H29: ='Data Input'!K132 -> 0 | I29: ='Data Input'!L132 -> 0
A30: Share application money | B30: ='Data Input'!E82 -> 0 | C30: ='Data Input'!F82 -> 0 | D30: ='Data Input'!G82 -> 0 | E30: ='Data Input'!H82 -> 0 | F30: ='Data Input'!I82 -> 0 | G30: ='Data Input'!J82 -> 0 | H30: ='Data Input'!K82 -> 0 | I30: ='Data Input'!L82 -> 0
A31: Total Borrowings | B31: ='Data Input'!E94+'Data Input'!E74+'Data Input'!E79+'Data Input'!E82-'Data Input'!E88 -> 0 | C31: ='Data Input'!F94+'Data Input'!F74+'Data Input'!F79+'Data Input'!F82-'Data Input'!F88 -> 0 | D31: ='Data Input'!G94+'Data Input'!G74+'Data Input'!G79+'Data Input'!G82-'Data Input'!G88 -> 0 | E31: ='Data Input'!H94+'Data Input'!H74+'Data Input'!H79+'Data Input'!H82-'Data Input'!H88 -> 0 | F31: ='Data Input'!I94+'Data Input'!I74+'Data Input'!I79+'Data Input'!I82-'Data Input'!I88 -> 33.25 | G31: ='Data Input'!J94+'Data Input'!J74+'Data Input'!J79+'Data Input'!J82-'Data Input'!J88 -> 45.88 | H31: ='Data Input'!K94+'Data Input'!K74+'Data Input'!K79+'Data Input'!K82-'Data Input'!K88 -> 79.05 | I31: ='Data Input'!L94+'Data Input'!L74+'Data Input'!L79+'Data Input'!L82-'Data Input'!L88 -> 78.03
A32: Secured | B32: ='Data Input'!E89+'Data Input'!E91+'Data Input'!E74+'Data Input'!E79 -> 0 | C32: ='Data Input'!F89+'Data Input'!F91+'Data Input'!F74+'Data Input'!F79 -> 0 | D32: ='Data Input'!G89+'Data Input'!G91+'Data Input'!G74+'Data Input'!G79 -> 0 | E32: ='Data Input'!H89+'Data Input'!H91+'Data Input'!H74+'Data Input'!H79 -> 0 | F32: ='Data Input'!I89+'Data Input'!I91+'Data Input'!I74+'Data Input'!I79 -> 25.3 | G32: ='Data Input'!J89+'Data Input'!J91+'Data Input'!J74+'Data Input'!J79 -> 38.98 | H32: ='Data Input'!K89+'Data Input'!K91+'Data Input'!K74+'Data Input'!K79 -> 72.15 | I32: ='Data Input'!L89+'Data Input'!L91+'Data Input'!L74+'Data Input'!L79 -> 71.13
A33: Unsecured | B33: ='Data Input'!E93+'Data Input'!E90+'Data Input'!E92 -> 0 | C33: ='Data Input'!F93+'Data Input'!F90+'Data Input'!F92 -> 0 | D33: ='Data Input'!G93+'Data Input'!G90+'Data Input'!G92 -> 0 | E33: ='Data Input'!H93+'Data Input'!H90+'Data Input'!H92 -> 0 | F33: ='Data Input'!I93+'Data Input'!I90+'Data Input'!I92 -> 7.95 | G33: ='Data Input'!J93+'Data Input'!J90+'Data Input'!J92 -> 6.9 | H33: ='Data Input'!K93+'Data Input'!K90+'Data Input'!K92 -> 6.9 | I33: ='Data Input'!L93+'Data Input'!L90+'Data Input'!L92 -> 6.9
A34: Other investments (excluding investments in allied concerns considered for arriving at Net Owned Funds) | B34: ='Data Input'!E128+'Data Input'!E130 -> 0 | C34: ='Data Input'!F128+'Data Input'!F130 -> 0 | D34: ='Data Input'!G128+'Data Input'!G130 -> 0 | E34: ='Data Input'!H128+'Data Input'!H130 -> 0 | F34: ='Data Input'!I128+'Data Input'!I130 -> 0.03 | G34: ='Data Input'!J128+'Data Input'!J130 -> 0.03 | H34: ='Data Input'!K128+'Data Input'!K130 -> 0.03 | I34: ='Data Input'!L128+'Data Input'!L130 -> 0.03
A35: Total Assets | B35: ='Data Input'!E137 -> 0 | C35: ='Data Input'!F137 -> 0 | D35: ='Data Input'!G137 -> 0 | E35: ='Data Input'!H137 -> 0 | F35: ='Data Input'!I137 -> 104.94 | G35: ='Data Input'!J137 -> 112.43 | H35: ='Data Input'!K137 -> 148.35 | I35: ='Data Input'!L137 -> 158.41
A36: Current Assets | B36: ='Data Input'!E122 -> 0 | C36: ='Data Input'!F122 -> 0 | D36: ='Data Input'!G122 -> 0 | E36: ='Data Input'!H122 -> 0 | F36: ='Data Input'!I122 -> 66.56 | G36: ='Data Input'!J122 -> 77.6 | H36: ='Data Input'!K122 -> 116.93 | I36: ='Data Input'!L122 -> 130.39
A37: Non Current Assets | B37: ='Data Input'!E135 -> 0 | C37: ='Data Input'!F135 -> 0 | D37: ='Data Input'!G135 -> 0 | E37: ='Data Input'!H135 -> 0 | F37: ='Data Input'!I135 -> 4.09 | G37: ='Data Input'!J135 -> 0.04 | H37: ='Data Input'!K135 -> 0.03 | I37: ='Data Input'!L135 -> 0.03
A38: Out of which net fixed assets | B38: ='Data Input'!E126 -> 0 | C38: ='Data Input'!F126 -> 0 | D38: ='Data Input'!G126 -> 0 | E38: ='Data Input'!H126 -> 0 | F38: ='Data Input'!I126 -> 34.29 | G38: ='Data Input'!J126 -> 34.79 | H38: ='Data Input'!K126 -> 31.39 | I38: ='Data Input'!L126 -> 27.99
A39: Current Liabilities | B39: ='Data Input'!E86 -> 0 | C39: ='Data Input'!F86 -> 0 | D39: ='Data Input'!G86 -> 0 | E39: ='Data Input'!H86 -> 0 | F39: ='Data Input'!I86 -> 54.1 | G39: ='Data Input'!J86 -> 59.28 | H39: ='Data Input'!K86 -> 89.05 | I39: ='Data Input'!L86 -> 91.58
A40: Net Working Capital | B40: ='Data Input'!E139 -> 0 | C40: ='Data Input'!F139 -> 0 | D40: ='Data Input'!G139 -> 0 | E40: ='Data Input'!H139 -> 0 | F40: ='Data Input'!I139 -> 12.46 | G40: ='Data Input'!J139 -> 18.32 | H40: ='Data Input'!K139 -> 27.88 | I40: ='Data Input'!L139 -> 38.81
A41: Current Ratio | B41: ='Data Input'!E140 -> #DIV/0! | C41: ='Data Input'!F140 -> #DIV/0! | D41: ='Data Input'!G140 -> #DIV/0! | E41: ='Data Input'!H140 -> #DIV/0! | F41: ='Data Input'!I140 -> 1.2303142 | G41: ='Data Input'!J140 -> 1.3090418 | H41: ='Data Input'!K140 -> 1.3130825 | I41: ='Data Input'!L140 -> 1.4237825
A42: Debt Equity Ratio | B42: =('Data Input'!E94)/'Data Input'!E101 -> #DIV/0! | C42: =('Data Input'!F94)/'Data Input'!F101 -> #DIV/0! | D42: =('Data Input'!G94)/'Data Input'!G101 -> #DIV/0! | E42: =('Data Input'!H94)/'Data Input'!H101 -> #DIV/0! | F42: =('Data Input'!I94)/'Data Input'!I101 -> 0.29826353 | G42: =('Data Input'!J94)/'Data Input'!J101 -> 0.20330541 | H42: =('Data Input'!K94)/'Data Input'!K101 -> 0.15662181 | I42: =('Data Input'!L94)/'Data Input'!L101 -> 0.11718489
A43: Debt Equity Ratio (Quasi) | B43: =('Data Input'!E94-'Data Input'!E93-'Data Input'!E90)/('Data Input'!E101+'Data Input'!E93) -> #DIV/0! | C43: =('Data Input'!F94-'Data Input'!F93-'Data Input'!F90)/('Data Input'!F101+'Data Input'!F93) -> #DIV/0! | D43: =('Data Input'!G94-'Data Input'!G93-'Data Input'!G90)/('Data Input'!G101+'Data Input'!G93) -> #DIV/0! | E43: =('Data Input'!H94-'Data Input'!H93-'Data Input'!H90)/('Data Input'!H101+'Data Input'!H93) -> #DIV/0! | F43: =('Data Input'!I94-'Data Input'!I93-'Data Input'!I90)/('Data Input'!I101+'Data Input'!I93) -> 0.22727273 | G43: =('Data Input'!J94-'Data Input'!J93-'Data Input'!J90)/('Data Input'!J101+'Data Input'!J93) -> 0.13085805 | H43: =('Data Input'!K94-'Data Input'!K93-'Data Input'!K90)/('Data Input'!K101+'Data Input'!K93) -> 0.094207139 | I43: =('Data Input'!L94-'Data Input'!L93-'Data Input'!L90)/('Data Input'!L101+'Data Input'!L93) -> 0.063691073
A44: Operating Profit/Sales | B44: =B15/B10 -> #DIV/0! | C44: =C15/C10 -> #DIV/0! | D44: =D15/D10 -> #DIV/0! | E44: =E15/E10 -> #DIV/0! | F44: =F15/F10 -> 0.018569049 | G44: =G15/G10 -> 0.014561046 | H44: =H15/H10 -> 0.017886855 | I44: =I15/I10 -> 0.019670828
A45: TOL/Adj TNW | B45: ='Data Input'!E95/B28 -> #DIV/0! | C45: ='Data Input'!F95/C28 -> #DIV/0! | D45: ='Data Input'!G95/D28 -> #DIV/0! | E45: ='Data Input'!H95/E28 -> #DIV/0! | F45: ='Data Input'!I95/F28 -> 1.6797753 | G45: ='Data Input'!J95/G28 -> 1.5453928 | H45: ='Data Input'!K95/H28 -> 1.893505 | I45: ='Data Input'!L95/I28 -> 1.648111
A46: Term liability/Adj TNW | B46: ='Data Input'!E94/'7A'!B28 -> #DIV/0! | C46: ='Data Input'!F94/'7A'!C28 -> #DIV/0! | D46: ='Data Input'!G94/'7A'!D28 -> #DIV/0! | E46: ='Data Input'!H94/'7A'!E28 -> #DIV/0! | F46: ='Data Input'!I94/'7A'!F28 -> 0.29826353 | G46: ='Data Input'!J94/'7A'!G28 -> 0.20330541 | H46: ='Data Input'!K94/'7A'!H28 -> 0.15662181 | I46: ='Data Input'!L94/'7A'!I28 -> 0.11718489
A47: Long Term Sources | B47: ='Data Input'!E101+'Data Input'!E94-'Data Input'!E136 -> 0 | C47: ='Data Input'!F101+'Data Input'!F94-'Data Input'!F136 -> 0 | D47: ='Data Input'!G101+'Data Input'!G94-'Data Input'!G136 -> 0 | E47: ='Data Input'!H101+'Data Input'!H94-'Data Input'!H136 -> 0 | F47: ='Data Input'!I101+'Data Input'!I94-'Data Input'!I136 -> 50.84 | G47: ='Data Input'!J101+'Data Input'!J94-'Data Input'!J136 -> 53.15 | H47: ='Data Input'!K101+'Data Input'!K94-'Data Input'!K136 -> 59.3 | I47: ='Data Input'!L101+'Data Input'!L94-'Data Input'!L136 -> 66.83
A48: Long Term Uses | B48: ='Data Input'!E126+'Data Input'!E135 -> 0 | C48: ='Data Input'!F126+'Data Input'!F135 -> 0 | D48: ='Data Input'!G126+'Data Input'!G135 -> 0 | E48: ='Data Input'!H126+'Data Input'!H135 -> 0 | F48: ='Data Input'!I126+'Data Input'!I135 -> 38.38 | G48: ='Data Input'!J126+'Data Input'!J135 -> 34.83 | H48: ='Data Input'!K126+'Data Input'!K135 -> 31.42 | I48: ='Data Input'!L126+'Data Input'!L135 -> 28.02
A49: Surplus/ Deficit | B49: =B47-B48 -> 0 | C49: =C47-C48 -> 0 | D49: =D47-D48 -> 0 | E49: =E47-E48 -> 0 | F49: =F47-F48 -> 12.46 | G49: =G47-G48 -> 18.32 | H49: =H47-H48 -> 27.88 | I49: =I47-I48 -> 38.81
A50: Short Term Sources | B50: ='Data Input'!E86 -> 0 | C50: ='Data Input'!F86 -> 0 | D50: ='Data Input'!G86 -> 0 | E50: ='Data Input'!H86 -> 0 | F50: ='Data Input'!I86 -> 54.1 | G50: ='Data Input'!J86 -> 59.28 | H50: ='Data Input'!K86 -> 89.05 | I50: ='Data Input'!L86 -> 91.58
A51: Short Term Uses | B51: ='Data Input'!E122 -> 0 | C51: ='Data Input'!F122 -> 0 | D51: ='Data Input'!G122 -> 0 | E51: ='Data Input'!H122 -> 0 | F51: ='Data Input'!I122 -> 66.56 | G51: ='Data Input'!J122 -> 77.6 | H51: ='Data Input'!K122 -> 116.93 | I51: ='Data Input'!L122 -> 130.39
A52: Surplus/ Deficit | B52: =B50-B51 -> 0 | C52: =C50-C51 -> 0 | D52: =D50-D51 -> 0 | E52: =E50-E51 -> 0 | F52: =F50-F51 -> -12.46 | G52: =G50-G51 -> -18.32 | H52: =H50-H51 -> -27.88 | I52: =I50-I51 -> -38.81

Sheet COP-MOF
A1: =+'Data Input'!B5 -> Punjab National Bank | G1: =+'Data Input'!B5 -> Punjab National Bank
A2: =+'Data Input'!B6 -> MCC Durgapur | G2: =+'Data Input'!B6 -> MCC Durgapur
A3: =+'Data Input'!B7 -> Durgapur | G3: =+'Data Input'!B7 -> Durgapur
A4: =+'Data Input'!B4 -> H R Ispat Pvt Ltd | G4: =+'Data Input'!B4 -> H R Ispat Pvt Ltd
A5: COST OF PROJECT | G5: List of Machinery
A6: Particulars | B6: Amt. | C6: Margin (%) | D6: Margin | E6: Elg. Loan | G6: S. No. | H6: Name of Machine | I6: Supplier | J6: Quot No. | K6: No. of Set | L6: Basic Cost/ Pc | M6: Total Basic Cost | N6: Tax | O6: Total
A7: Land | C7: 0.4 | D7: =IF(B7="", "", B7*C7) | E7: 0
A8: Building | C8: 0.25 | D8: =IF(B8="", "", B8*C8) | E8: =B8-D8 -> #VALUE!
A9: Plant & Machinery | C9: 0.05 | D9: =IF(B9="", "", B9*C9) | E9: =B9-D9 -> #VALUE!
A10: Others | C10: 0.25 | D10: =IF(B10="", "", B10*C10) | E10: =B10-D10 -> #VALUE!
A11: Misc. | C11: 0.25 | D11: =IF(B11="", "", B11*C11) | E11: =B11-D11 -> #VALUE!
A12: Total Hard Cost | B12: =IF(SUM(B7:B11)=0, "", SUM(B7:B11)) | D12: =IF(SUM(D7:D11)=0, "", SUM(D7:D11)) | E12: =IF(SUM(E7:E11)=0, "", SUM(E7:E11)) -> #VALUE!
A13: Interest During Construction | C13: 0
A14: Contingency | C14: 0
A15: Other Prelim. Pre-Op Expenses | C15: 0
A16: Total Cost | B16: =IF(SUM(B12:B15)=0, "", SUM(B12:B15)) | D16: =IF(SUM(D12:D15)=0, "", SUM(D12:D15)) | E16: =IF(SUM(E12:E15)=0, "", SUM(E12:E15)) -> #VALUE!
A17: MEANS OF FINANCE
A18: Particulars | B18: Amt. | C18: %age
A19: Promoter's Margin | C19: =IF(B19/B16="", "", B19/B16) -> #VALUE!
A20: Share Capital | C20: =IF(B20/B16="", "", B20/B16) -> #VALUE!
A21: Internal Accrual | C21: =IF(B21/B16="", "", B21/B16) -> #VALUE!
A22: Unsecured Loans | C22: =IF(B22/B16="", "", B22/B16) -> #VALUE!
A23: Preference shares | C23: =IF(B23/B16="", "", B23/B16) -> #VALUE!
A24: Bank Loan | C24: =B24/B16 -> #VALUE!
A25: Other Third Party Sources | C25: =B25/B16 -> #VALUE!
A26: Total Means of Finance | B26: =IF(SUM(B20:B25)=0, "", SUM(B20:B25))

Sheet DSCR & IRR
A1: =+'Data Input'!B5 -> Punjab National Bank
A2: =+'Data Input'!B6 -> MCC Durgapur
A3: =+'Data Input'!B7 -> Durgapur
A4: =+'Data Input'!B4 -> H R Ispat Pvt Ltd
A5: DSCR CALCULATION | B5: =IF('Data Input'!I10="", "", 'Data Input'!I10) -> Audited | C5: =IF('Data Input'!J10="", "", 'Data Input'!J10) -> Audited | D5: =IF('Data Input'!K10="", "", 'Data Input'!K10) -> Projected | E5: =IF('Data Input'!L10="", "", 'Data Input'!L10) -> Projected | F5: =IF('Data Input'!#REF!="", "", 'Data Input'!#REF!) -> #REF! | G5: =IF('Data Input'!#REF!="", "", 'Data Input'!#REF!) -> #REF! | H5: =IF('Data Input'!#REF!="", "", 'Data Input'!#REF!) -> #REF! | I5: =IF('Data Input'!#REF!="", "", 'Data Input'!#REF!) -> #REF! | J5: =IF('Data Input'!#REF!="", "", 'Data Input'!#REF!) -> #REF! | K5: =IF('Data Input'!#REF!="", "", 'Data Input'!#REF!) -> #REF! | L5: =IF('Data Input'!#REF!="", "", 'Data Input'!#REF!) -> #REF!
A6: YEAR ENDING 31ST MARCH | B6: =IF('Data Input'!J11="", "", 'Data Input'!J11) -> 2024 | C6: =IF('Data Input'!K11="", "", 'Data Input'!K11) -> 2025 | D6: =IF('Data Input'!L11="", "", 'Data Input'!L11) -> 2026 | E6: =IF('Data Input'!#REF!="", "", 'Data Input'!#REF!) -> #REF! | F6: =IF('Data Input'!#REF!="", "", 'Data Input'!#REF!) -> #REF! | G6: =IF('Data Input'!#REF!="", "", 'Data Input'!#REF!) -> #REF! | H6: =IF('Data Input'!#REF!="", "", 'Data Input'!#REF!) -> #REF! | I6: =IF('Data Input'!#REF!="", "", 'Data Input'!#REF!) -> #REF! | J6: =IF('Data Input'!#REF!="", "", 'Data Input'!#REF!) -> #REF! | K6: =IF('Data Input'!#REF!="", "", 'Data Input'!#REF!) -> #REF! | L6: =IF('Data Input'!#REF!="", "", 'Data Input'!#REF!) -> #REF!
A7: NET PROFIT | B7: ='Data Input'!J57 -> 4.79 | C7: ='Data Input'!K57 -> 6.84 | D7: ='Data Input'!L57 -> 8.12 | E7: ='Data Input'!#REF! -> #REF! | F7: ='Data Input'!#REF! -> #REF! | G7: ='Data Input'!#REF! -> #REF! | H7: ='Data Input'!#REF! -> #REF! | I7: ='Data Input'!#REF! -> #REF! | J7: ='Data Input'!#REF! -> #REF! | K7: ='Data Input'!#REF! -> #REF! | L7: ='Data Input'!#REF! -> #REF!
A8: DEPRECIATION | B8: ='Data Input'!J29 -> 3.47 | C8: ='Data Input'!K29 -> 3.4 | D8: ='Data Input'!L29 -> 3.4 | E8: ='Data Input'!#REF! -> #REF! | F8: ='Data Input'!#REF! -> #REF! | G8: ='Data Input'!#REF! -> #REF! | H8: ='Data Input'!#REF! -> #REF! | I8: ='Data Input'!#REF! -> #REF! | J8: ='Data Input'!#REF! -> #REF! | K8: ='Data Input'!#REF! -> #REF! | L8: ='Data Input'!#REF! -> #REF!
A9: INTEREST ON LONG TERM LOANS | B9: ='Data Input'!J47 -> 0.6 | C9: ='Data Input'!K47 -> 0.21 | D9: ='Data Input'!L47 -> 0.12 | E9: ='Data Input'!#REF! -> #REF! | F9: ='Data Input'!#REF! -> #REF! | G9: ='Data Input'!#REF! -> #REF! | H9: ='Data Input'!#REF! -> #REF! | I9: ='Data Input'!#REF! -> #REF! | J9: ='Data Input'!#REF! -> #REF! | K9: ='Data Input'!#REF! -> #REF! | L9: ='Data Input'!#REF! -> #REF!
A10: OTHER NON CASH EXPENDITURE | B10: ='Data Input'!J56 -> 0 | C10: ='Data Input'!K56 -> 0 | D10: ='Data Input'!L56 -> 0 | E10: ='Data Input'!#REF! -> #REF! | F10: ='Data Input'!#REF! -> #REF! | G10: ='Data Input'!#REF! -> #REF! | H10: ='Data Input'!#REF! -> #REF! | I10: ='Data Input'!#REF! -> #REF! | J10: ='Data Input'!#REF! -> #REF! | K10: ='Data Input'!#REF! -> #REF! | L10: ='Data Input'!#REF! -> #REF!
A11: TOTAL (A) | B11: =SUM(B7:B10) -> 8.86 | C11: =SUM(C7:C10) -> 10.45 | D11: =SUM(D7:D10) -> 11.64 | E11: =SUM(E7:E10) -> #REF! | F11: =SUM(F7:F10) -> #REF! | G11: =SUM(G7:G10) -> #REF! | H11: =SUM(H7:H10) -> #REF! | I11: =SUM(I7:I10) -> #REF! | ... L11: =SUM(L7:L10) -> #REF!
A12: INTEREST ON LONG TERM LOANS | B12: ='Data Input'!J47 -> 0.6 | C12: ='Data Input'!K47 -> 0.21 | D12: ='Data Input'!L47 -> 0.12 | E12: ='Data Input'!#REF! -> #REF! | F12: ='Data Input'!#REF! -> #REF! | G12: ='Data Input'!#REF! -> #REF! | H12: ='Data Input'!#REF! -> #REF! | I12: ='Data Input'!#REF! -> #REF! | J12: ='Data Input'!#REF! -> #REF! | K12: ='Data Input'!#REF! -> #REF! | L12: ='Data Input'!#REF! -> #REF!
A13: PRINCIPLE PAYMENT OF TERM LOAN | B13: ='Data Input'!I79 -> 2.42 | C13: ='Data Input'!J79 -> 2.39 | D13: ='Data Input'!K79 -> 1.02 | E13: ='Data Input'!L79 -> 1.02 | F13: ='Data Input'!#REF! -> #REF! | G13: ='Data Input'!#REF! -> #REF! | H13: ='Data Input'!#REF! -> #REF! | I13: ='Data Input'!#REF! -> #REF! | J13: ='Data Input'!#REF! -> #REF! | K13: ='Data Input'!#REF! -> #REF! | L13: ='Data Input'!#REF! -> #REF!
A14: TOTAL (B) | B14: =SUM(B12:B13) -> 3.02 | C14: =SUM(C12:C13) -> 2.6 | D14: =SUM(D12:D13) -> 1.14 | E14: =SUM(E12:E13) -> #REF! | F14: =SUM(F12:F13) -> #REF! | G14: =SUM(G12:G13) -> #REF! | H14: =SUM(H12:H13) -> #REF! | I14: =SUM(I12:I13) -> #REF! | ... L14: =SUM(L12:L13) -> #REF!
A15: DSCR (A/B) | B15: =B11/B14 -> 2.9337748 | C15: =C11/C14 -> 4.0192308 | D15: =D11/D14 -> 10.210526 | E15: =E11/E14 -> #REF! | F15: =F11/F14 -> #REF! | G15: =G11/G14 -> #REF! | H15: =H11/H14 -> #REF! | I15: =I11/I14 -> #REF! | ... L15: =L11/L14 -> #REF!
A16: Average DSCR | B16: =SUM(B11:H11)/SUM(B14:H14) -> #REF!
B17: =B8+B7 -> 8.26 | C17: =C8+C7 -> 10.24 | D17: =D8+D7 -> 11.52 | E17: =E8+E7 -> #REF! | F17: =F8+F7 -> #REF! | G17: =G8+G7 -> #REF! | H17: =H8+H7 -> #REF! | I17: =I8+I7 -> #REF!
A18: IRR CALCULATION | B18: =+B5 -> Audited | C18: =+C5 -> Audited | D18: =+D5 -> Projected | E18: =+E5 -> Projected | F18: =+F5 -> #REF! | G18: =+G5 -> #REF! | H18: =+H5 -> #REF! | I18: =+I5 -> #REF! | ... L18: =+L5 -> #REF!
A19: YEAR ENDING 31ST MARCH | B19: =+B6 -> 2024 | C19: =+C6 -> 2025 | D19: =+D6 -> 2026 | E19: =+E6 -> #REF! | F19: =+F6 -> #REF! | G19: =+G6 -> #REF! | H19: =+H6 -> #REF! | I19: =+I6 -> #REF! | ... L19: =+L6 -> #REF!
A20: Year | B20: 0 | C20: 1 | D20: 2 | E20: 3 | F20: 4 | G20: 5 | H20: 6 | I20: 7 | J20: 8 | K20: 9 | L20: 10
A21: CAPEX Value | B21: =-'COP-MOF'!B16 -> #VALUE!
A22: Cash Accrual | B22: =B7+B8+B10 -> 8.26 | C22: =C7+C8+C10 -> 10.24 | D22: =D7+D8+D10 -> 11.52 | E22: =E7+E8+E10 -> #REF! | F22: =F7+F8+F10 -> #REF! | G22: =G7+G8+G10 -> #REF! | H22: =H7+H8+H10 -> #REF! | I22: =I7+I8+I10 -> #REF! | ... L22: =L7+L8+L10 -> #REF!
A23: Cash Flow | B23: =B21+B22 -> #VALUE! | C23: =C21+C22 -> 10.24 | D23: =D21+D22 -> 11.52 | E23: =E21+E22 -> #REF! | F23: =F21+F22 -> #REF! | G23: =G21+G22 -> #REF! | H23: =H21+H22 -> #REF! | I23: =I21+I22 -> #REF! | ... L23: =L21+L22 -> #REF! | M23: =IF(L23=0, IRR(B23:K23), IF(K23=0, IRR(B23:J23), IF(J23=0, IRR(B23:I23), IF(I23=0, IRR(B23:H23), IF(H23=0, IRR(B23:G23), IF(G23=0, IRR(B23:F23), IF(F23=0, IRR(B23:E23), IF(E23=0, IRR(B23:D23), IF(D23=0, IRR(B23:C23), IF(C23=0, IRR(B23), IRR(B23:L23))))))))))) -> #REF!
A24: IRR | B24: =+M23 -> #REF!

Sheet BEP
A1: =+'Data Input'!B5 -> Punjab National Bank
A2: =+'Data Input'!B6 -> MCC Durgapur
A3: =+'Data Input'!B7 -> Durgapur
A4: =+'Data Input'!B4 -> H R Ispat Pvt Ltd
B5: =IF('Data Input'!I10="", "", 'Data Input'!I10) -> Audited | C5: =IF('Data Input'!J10="", "", 'Data Input'!J10) -> Audited | D5: =IF('Data Input'!K10="", "", 'Data Input'!K10) -> Projected | E5: =IF('Data Input'!L10="", "", 'Data Input'!L10) -> Projected | F5: =IF('Data Input'!#REF!="", "", 'Data Input'!#REF!) -> #REF! | G5: =IF('Data Input'!#REF!="", "", 'Data Input'!#REF!) -> #REF! | H5: =IF('Data Input'!#REF!="", "", 'Data Input'!#REF!) -> #REF! | I5: =IF('Data Input'!#REF!="", "", 'Data Input'!#REF!) -> #REF! | J5: =IF('Data Input'!#REF!="", "", 'Data Input'!#REF!) -> #REF! | K5: =IF('Data Input'!#REF!="", "", 'Data Input'!#REF!) -> #REF! | L5: =IF('Data Input'!#REF!="", "", 'Data Input'!#REF!) -> #REF!
A6: YEAR ENDING 31ST MARCH | B6: =IF('Data Input'!I11="", "", 'Data Input'!I11) -> 2023 | C6: =IF('Data Input'!J11="", "", 'Data Input'!J11) -> 2024 | D6: =IF('Data Input'!K11="", "", 'Data Input'!K11) -> 2025 | E6: =IF('Data Input'!L11="", "", 'Data Input'!L11) -> 2026 | F6: =IF('Data Input'!#REF!="", "", 'Data Input'!#REF!) -> #REF! | G6: =IF('Data Input'!#REF!="", "", 'Data Input'!#REF!) -> #REF! | H6: =IF('Data Input'!#REF!="", "", 'Data Input'!#REF!) -> #REF! | I6: =IF('Data Input'!#REF!="", "", 'Data Input'!#REF!) -> #REF! | J6: =IF('Data Input'!#REF!="", "", 'Data Input'!#REF!) -> #REF! | K6: =IF('Data Input'!#REF!="", "", 'Data Input'!#REF!) -> #REF! | L6: =IF('Data Input'!#REF!="", "", 'Data Input'!#REF!) -> #REF!
A7: FIXED COST
A8: Depreciation | B8: ='Data Input'!I29 -> 3.23 | C8: ='Data Input'!J29 -> 3.47 | D8: ='Data Input'!K29 -> 3.4 | E8: ='Data Input'!L29 -> 3.4 | F8: ='Data Input'!#REF! -> #REF! | G8: ='Data Input'!#REF! -> #REF! | H8: ='Data Input'!#REF! -> #REF! | I8: ='Data Input'!#REF! -> #REF! | J8: ='Data Input'!#REF! -> #REF! | K8: ='Data Input'!#REF! -> #REF! | L8: ='Data Input'!#REF! -> #REF!
A9: =+'[2]TEV-Profitability Total'!A29:B29 -> Administrative & Selling Expenses | B9: ='Data Input'!I40 -> 1.92 | C9: ='Data Input'!J40 -> 3.6 | D9: ='Data Input'!K40 -> 3.17 | E9: ='Data Input'!L40 -> 3.62 | F9: ='Data Input'!#REF! -> #REF! | G9: ='Data Input'!#REF! -> #REF! | H9: ='Data Input'!#REF! -> #REF! | I9: ='Data Input'!#REF! -> #REF! | J9: ='Data Input'!#REF! -> #REF! | K9: ='Data Input'!#REF! -> #REF! | L9: ='Data Input'!#REF! -> #REF!
A10: Interest on Term Loan | B10: ='Data Input'!I47 -> 0.5 | C10: ='Data Input'!J47 -> 0.6 | D10: ='Data Input'!K47 -> 0.21 | E10: ='Data Input'!L47 -> 0.12 | F10: ='Data Input'!#REF! -> #REF! | G10: ='Data Input'!#REF! -> #REF! | H10: ='Data Input'!#REF! -> #REF! | I10: ='Data Input'!#REF! -> #REF! | J10: ='Data Input'!#REF! -> #REF! | K10: ='Data Input'!#REF! -> #REF! | L10: ='Data Input'!#REF! -> #REF!
A11: Cost of Production (Excl RM Cost & Depreciation) | B11: ='Data Input'!I35-'Data Input'!I29-'Data Input'!I21-'Data Input'!I24-'Data Input'!I25 -> 73.29 | C11: ='Data Input'!J35-'Data Input'!J29-'Data Input'!J21-'Data Input'!J24-'Data Input'!J25 -> 63.9 | D11: ='Data Input'!K35-'Data Input'!K29-'Data Input'!K21-'Data Input'!K24-'Data Input'!K25 -> 73.06 | E11: ='Data Input'!L35-'Data Input'!L29-'Data Input'!L21-'Data Input'!L24-'Data Input'!L25 -> 82.98 | F11: ='Data Input'!#REF!-'Data Input'!#REF!-'Data Input'!#REF!-'Data Input'!#REF!-'Data Input'!#REF! -> #REF! | G11: ='Data Input'!#REF!-'Data Input'!#REF!-'Data Input'!#REF!-'Data Input'!#REF!-'Data Input'!#REF! -> #REF! | H11: ='Data Input'!#REF!-'Data Input'!#REF!-'Data Input'!#REF!-'Data Input'!#REF!-'Data Input'!#REF! -> #REF! | I11: ='Data Input'!#REF!-'Data Input'!#REF!-'Data Input'!#REF!-'Data Input'!#REF!-'Data Input'!#REF! -> #REF! | J11: ='Data Input'!#REF!-'Data Input'!#REF!-'Data Input'!#REF!-'Data Input'!#REF!-'Data Input'!#REF! -> #REF! | K11: ='Data Input'!#REF!-'Data Input'!#REF!-'Data Input'!#REF!-'Data Input'!#REF!-'Data Input'!#REF! -> #REF! | L11: ='Data Input'!#REF!-'Data Input'!#REF!-'Data Input'!#REF!-'Data Input'!#REF!-'Data Input'!#REF! -> #REF!
A12: 30% of Cost of Prod. (Excl. RM Cost) | B12: =+B11*30% -> 21.987 | C12: =+C11*30% -> 19.17 | D12: =+D11*30% -> 21.918 | E12: =+E11*30% -> 24.894 | F12: =+F11*30% -> #REF! | G12: =+G11*30% -> #REF! | H12: =+H11*30% -> #REF! | I12: =+I11*30% -> #REF! | ... L12: =+L11*30% -> #REF!
A13: TOTAL FIXED COST (F) | B13: =SUM(B8:B10)+B12 -> 27.637 | C13: =SUM(C8:C10)+C12 -> 26.84 | D13: =SUM(D8:D10)+D12 -> 28.698 | E13: =SUM(E8:E10)+E12 -> 32.034 | F13: =SUM(F8:F10)+F12 -> #REF! | G13: =SUM(G8:G10)+G12 -> #REF! | H13: =SUM(H8:H10)+H12 -> #REF! | I13: =SUM(I8:I10)+I12 -> #REF! | ... L13: =SUM(L8:L10)+L12 -> #REF!
A14: PROFIT BEFOR TAX (P) | B14: ='Data Input'!I54 -> 10.58 | C14: ='Data Input'!J54 -> 7.01 | D14: ='Data Input'!K54 -> 9.66 | E14: ='Data Input'!L54 -> 12.1 | F14: ='Data Input'!#REF! -> #REF! | G14: ='Data Input'!#REF! -> #REF! | H14: ='Data Input'!#REF! -> #REF! | I14: ='Data Input'!#REF! -> #REF! | J14: ='Data Input'!#REF! -> #REF! | K14: ='Data Input'!#REF! -> #REF! | L14: ='Data Input'!#REF! -> #REF!
A15: BEP ON GIVEN SALES (= F/(F+P) ) | B15: =B13/(B13+B14) -> 0.72315985 | C15: =C13/(C13+C14) -> 0.7929099 | D15: =D13/(D13+D14) -> 0.74816205 | E15: =E13/(E13+E14) -> 0.72583496 | F15: =F13/(F13+F14) -> #REF! | G15: =G13/(G13+G14) -> #REF! | H15: =H13/(H13+H14) -> #REF! | I15: =I13/(I13+I14) -> #REF! | ... L15: =L13/(L13+L14) -> #REF!
A16: CASH BEP ON Given Gross Sales | B16: =(B13-B8)/(B13+B14) -> 0.63864249 | C16: =(C13-C8)/(C13+C14) -> 0.69039882 | D16: =(D13-D8)/(D13+D14) -> 0.65952344 | E16: =(E13-E8)/(E13+E14) -> 0.64879685 | F16: =(F13-F8)/(F13+F14) -> #REF! | G16: =(G13-G8)/(G13+G14) -> #REF! | H16: =(H13-H8)/(H13+H14) -> #REF! | I16: =(I13-I8)/(I13+I14) -> #REF! | ... L16: =(L13-L8)/(L13+L14) -> #REF!
A17: BEP IN TERMS OF SALES | B17: =B15*H18 -> 0 | C17: =C15*I18 -> 0 | D17: =D15*J18 -> 0 | E17: =E15*K18 -> 0 | F17: =F15*L18 -> #REF! | G17: =G15*M18 -> #REF! | H17: =H15*N18 -> #REF! | I17: =I15*O18 -> #REF! | ... L17: =L15*R18 -> #REF!
A18: CAPACITY UTILIZATION
A19: BEP ON UTILIZED CAPACITY | B19: =+B15*B18 -> 0 | C19: =+C15*C18 -> 0 | D19: =+D15*D18 -> 0 | E19: =+E15*E18 -> 0 | F19: =+F15*F18 -> #REF! | G19: =+G15*G18 -> #REF! | H19: =+H15*H18 -> #REF! | I19: =+I15*I18 -> #REF! | ... L19: =+L15*L18 -> #REF!
A20: CASH BEP ON UTILIZED CAPACITY | B20: =B18*B16 -> 0 | C20: =C18*C16 -> 0 | D20: =D18*D16 -> 0 | E20: =E18*E16 -> 0 | F20: =F18*F16 -> #REF! | G20: =G18*G16 -> #REF! | H20: =H18*H16 -> #REF! | I20: =I18*I16 -> #REF! | ... L20: =L18*L16 -> #REF!
A21: Break Even Point in Viability Year | E21: =+E15 -> 0.72583496
A22: Break Even Net Sales in Viability Year | E22: =+E17 -> 0

Sheet Sensitivity
B1: ='Data Input'!B5 -> Punjab National Bank
B2: ='Data Input'!B6 -> MCC Durgapur
B3: ='Data Input'!B7 -> Durgapur
B4: ='Data Input'!B4 -> H R Ispat Pvt Ltd
B5: CASE I | C5: =IF('Data Input'!I10="", "", 'Data Input'!I10) -> Audited | D5: =IF('Data Input'!J10="", "", 'Data Input'!J10) -> Audited | E5: =IF('Data Input'!K10="", "", 'Data Input'!K10) -> Projected | F5: =IF('Data Input'!L10="", "", 'Data Input'!L10) -> Projected | G5: =IF('Data Input'!#REF!="", "", 'Data Input'!#REF!) -> #REF! | H5: =IF('Data Input'!#REF!="", "", 'Data Input'!#REF!) -> #REF! | I5: =IF('Data Input'!#REF!="", "", 'Data Input'!#REF!) -> #REF! | J5: =IF('Data Input'!#REF!="", "", 'Data Input'!#REF!) -> #REF!
A6: Case I | B6: Raw Material Cost Up by 5% | C6: =IF('Data Input'!J11="", "", 'Data Input'!J11) -> 2024 | D6: =IF('Data Input'!K11="", "", 'Data Input'!K11) -> 2025 | E6: =IF('Data Input'!L11="", "", 'Data Input'!L11) -> 2026 | F6: =IF('Data Input'!#REF!="", "", 'Data Input'!#REF!) -> #REF! | G6: =IF('Data Input'!#REF!="", "", 'Data Input'!#REF!) -> #REF! | H6: =IF('Data Input'!#REF!="", "", 'Data Input'!#REF!) -> #REF! | I6: =IF('Data Input'!#REF!="", "", 'Data Input'!#REF!) -> #REF! | J6: =IF('Data Input'!#REF!="", "", 'Data Input'!#REF!) -> #REF!
A7: 1 | B7: Net Sales | C7: ='Data Input'!J18 -> 471.12 | D7: ='Data Input'!K18 -> 528.88 | E7: ='Data Input'!L18 -> 603.94 | F7: ='Data Input'!#REF! -> #REF! | G7: ='Data Input'!#REF! -> #REF! | H7: ='Data Input'!#REF! -> #REF! | I7: ='Data Input'!#REF! -> #REF! | J7: ='Data Input'!#REF! -> #REF!
A8: 1.05 | B8: Raw Material Cost (Up by 5%) | C8: ='Data Input'!J21*$A$8 -> 403.5885 | D8: ='Data Input'!K21*$A$8 -> 457.674 | E8: ='Data Input'!L21*$A$8 -> 515.844 | F8: ='Data Input'!#REF!*$A$8 -> #REF! | G8: ='Data Input'!#REF!*$A$8 -> #REF! | H8: ='Data Input'!#REF!*$A$8 -> #REF! | I8: ='Data Input'!#REF!*$A$8 -> #REF! | J8: ='Data Input'!#REF!*$A$8 -> #REF!
A9: 1 | B9: Other Expenses | C9: =C7-'Data Input'!J54-'Data Input'!J21 -> 79.74 | D9: =D7-'Data Input'!K54-'Data Input'!K21 -> 83.34 | E9: =E7-'Data Input'!L54-'Data Input'!L21 -> 100.56 | F9: =F7-'Data Input'!#REF!-'Data Input'!#REF! -> #REF! | G9: =G7-'Data Input'!#REF!-'Data Input'!#REF! -> #REF! | H9: =H7-'Data Input'!#REF!-'Data Input'!#REF! -> #REF! | I9: =I7-'Data Input'!#REF!-'Data Input'!#REF! -> #REF! | J9: =J7-'Data Input'!#REF!-'Data Input'!#REF! -> #REF!
B10: Profit Before Tax | C10: =C7-C8-C9 -> -12.2085 | D10: =D7-D8-D9 -> -12.134 | E10: =E7-E8-E9 -> -12.464 | F10: =F7-F8-F9 -> #REF! | G10: =G7-G8-G9 -> #REF! | H10: =H7-H8-H9 -> #REF! | I10: =I7-I8-I9 -> #REF! | J10: =J7-J8-J9 -> #REF!
B11: Tax | C11: ='Tax Calulator - Ref'!C31 -> 0 | D11: ='Tax Calulator - Ref'!D31 -> 0 | E11: ='Tax Calulator - Ref'!E31 -> 0 | F11: ='Tax Calulator - Ref'!F31 -> #REF! | G11: ='Tax Calulator - Ref'!G31 -> #REF! | H11: ='Tax Calulator - Ref'!H31 -> #REF! | I11: ='Tax Calulator - Ref'!I31 -> #REF! | J11: ='Tax Calulator - Ref'!J31 -> #REF!
B12: Profit After Tax | C12: =C10-C11 -> -12.2085 | D12: =D10-D11 -> -12.134 | E12: =E10-E11 -> -12.464 | F12: =F10-F11 -> #REF! | G12: =G10-G11 -> #REF! | H12: =H10-H11 -> #REF! | I12: =I10-I11 -> #REF! | J12: =J10-J11 -> #REF!
B13: Depreciation | C13: ='Data Input'!J29 -> 3.47 | D13: ='Data Input'!K29 -> 3.4 | E13: ='Data Input'!L29 -> 3.4 | F13: ='Data Input'!#REF! -> #REF! | G13: ='Data Input'!#REF! -> #REF! | H13: ='Data Input'!#REF! -> #REF! | I13: ='Data Input'!#REF! -> #REF! | J13: ='Data Input'!#REF! -> #REF!
B14: DSCR Calculation - Case I
B15: PAT | C15: =+C12 -> -12.2085 | D15: =+D12 -> -12.134 | E15: =+E12 -> -12.464 | F15: =+F12 -> #REF! | G15: =+G12 -> #REF! | H15: =+H12 -> #REF! | I15: =+I12 -> #REF! | J15: =+J12 -> #REF!
B16: Depreciation | C16: =+C13 -> 3.47 | D16: =+D13 -> 3.4 | E16: =+E13 -> 3.4 | F16: =+F13 -> #REF! | G16: =+G13 -> #REF! | H16: =+H13 -> #REF! | I16: =+I13 -> #REF! | J16: =+J13 -> #REF!
B17: Interest on LTB | C17: =+'DSCR & IRR'!B12 -> 0.6 | D17: =+'DSCR & IRR'!C12 -> 0.21 | E17: =+'DSCR & IRR'!D12 -> 0.12 | F17: =+'DSCR & IRR'!E12 -> #REF! | G17: =+'DSCR & IRR'!F12 -> #REF! | H17: =+'DSCR & IRR'!G12 -> #REF! | I17: =+'DSCR & IRR'!H12 -> #REF! | J17: =+'DSCR & IRR'!I12 -> #REF!
B18: Deferred Tax Liability | C18: 0 | D18: 0 | E18: 0 | F18: 0 | G18: 0 | H18: 0 | I18: 0 | J18: 0
B19: Total A | C19: =SUM(C15:C18) -> -8.1385 | D19: =SUM(D15:D18) -> -8.524 | E19: =SUM(E15:E18) -> -8.944 | F19: =SUM(F15:F18) -> #REF! | G19: =SUM(G15:G18) -> #REF! | H19: =SUM(H15:H18) -> #REF! | I19: =SUM(I15:I18) -> #REF! | J19: =SUM(J15:J18) -> #REF!
B20: Interest on LTB | C20: =+C17 -> 0.6 | D20: =+D17 -> 0.21 | E20: =+E17 -> 0.12 | F20: =+F17 -> #REF! | G20: =+G17 -> #REF! | H20: =+H17 -> #REF! | I20: =+I17 -> #REF! | J20: =+J17 -> #REF!
B21: Principle Repayment | C21: ='DSCR & IRR'!B13 -> 2.42 | D21: ='DSCR & IRR'!C13 -> 2.39 | E21: ='DSCR & IRR'!D13 -> 1.02 | F21: ='DSCR & IRR'!E13 -> 1.02 | G21: ='DSCR & IRR'!F13 -> #REF! | H21: ='DSCR & IRR'!G13 -> #REF! | I21: ='DSCR & IRR'!H13 -> #REF! | J21: ='DSCR & IRR'!I13 -> #REF!
B22: Total B | C22: =SUM(C20:C21) -> 3.02 | D22: =SUM(D20:D21) -> 2.6 | E22: =SUM(E20:E21) -> 1.14 | F22: =SUM(F20:F21) -> #REF! | G22: =SUM(G20:G21) -> #REF! | H22: =SUM(H20:H21) -> #REF! | I22: =SUM(I20:I21) -> #REF! | J22: =SUM(J20:J21) -> #REF!
B23: DSCR (A/B) | C23: =+C19/C22 -> -2.6948675 | D23: =+D19/D22 -> -3.2784615 | E23: =+E19/E22 -> -7.845614 | F23: =+F19/F22 -> #REF! | G23: =+G19/G22 -> #REF! | H23: =+H19/H22 -> #REF! | I23: =+I19/I22 -> #REF! | J23: =+J19/J22 -> #REF!
B24: Avg. DSCR (∑A/∑B) | C24: =SUM(C19:I19)/SUM(C22:I22) -> #REF!
B25: IRR Calculation - Case I
B26: Cost of Project | C26: ='DSCR & IRR'!B21 -> #VALUE! | D26: ='DSCR & IRR'!C21 -> 0 | E26: ='DSCR & IRR'!D21 -> 0 | F26: ='DSCR & IRR'!E21 -> 0 | G26: ='DSCR & IRR'!F21 -> 0 | H26: ='DSCR & IRR'!G21 -> 0 | I26: ='DSCR & IRR'!H21 -> 0 | J26: ='DSCR & IRR'!I21 -> 0
B27: Cash Inflow | C27: =+C19-C17 -> -8.7385 | D27: =+D19-D17 -> -8.734 | E27: =+E19-E17 -> -9.064 | F27: =+F19-F17 -> #REF! | G27: =+G19-G17 -> #REF! | H27: =+H19-H17 -> #REF! | I27: =+I19-I17 -> #REF! | J27: =+J19-J17 -> #REF! | K27: =+K19-K17 -> 0
B28: IRR - Case I | C28: =K27 -> 0
B29: CASE II | C29: =C5 -> Audited | D29: =D5 -> Audited | E29: =E5 -> Projected | F29: =F5 -> Projected | G29: =G5 -> #REF! | H29: =H5 -> #REF! | I29: =I5 -> #REF! | J29: =J5 -> #REF!
A30: Case II | B30: Sale Down by 5% | C30: =C6 -> 2024 | D30: =D6 -> 2025 | E30: =E6 -> 2026 | F30: =F6 -> #REF! | G30: =G6 -> #REF! | H30: =H6 -> #REF! | I30: =I6 -> #REF! | J30: =J6 -> #REF!
A31: 0.95 | B31: Sales (Down by 5%) | C31: ='Data Input'!J18*$A$31 -> 447.564 | D31: ='Data Input'!K18*$A$31 -> 502.436 | E31: ='Data Input'!L18*$A$31 -> 573.743 | F31: ='Data Input'!#REF!*$A$31 -> #REF! | G31: ='Data Input'!#REF!*$A$31 -> #REF! | H31: ='Data Input'!#REF!*$A$31 -> #REF! | I31: ='Data Input'!#REF!*$A$31 -> #REF! | J31: ='Data Input'!#REF!*$A$31 -> #REF!
A32: 1 | B32: Raw Material Cost | C32: ='Data Input'!J21*$A$32 -> 384.37 | D32: ='Data Input'!K21*$A$32 -> 435.88 | E32: ='Data Input'!L21*$A$32 -> 491.28 | F32: ='Data Input'!#REF!*$A$32 -> #REF! | G32: ='Data Input'!#REF!*$A$32 -> #REF! | H32: ='Data Input'!#REF!*$A$32 -> #REF! | I32: ='Data Input'!#REF!*$A$32 -> #REF! | J32: ='Data Input'!#REF!*$A$32 -> #REF! | K32: ='Data Input'!#REF!*$A$32 -> #REF!
A33: 1 | B33: Other Expenses (Constant) | C33: =C9*$A$33 -> 79.74 | D33: =D9*$A$33 -> 83.34 | E33: =E9*$A$33 -> 100.56 | F33: =F9*$A$33 -> #REF! | G33: =G9*$A$33 -> #REF! | H33: =H9*$A$33 -> #REF! | I33: =I9*$A$33 -> #REF! | J33: =J9*$A$33 -> #REF! | K33: =K9*$A$33 -> 0
B34: Profit Before Tax | C34: =+C31-C32-C33 -> -16.546 | D34: =+D31-D32-D33 -> -16.784 | E34: =+E31-E32-E33 -> -18.097 | F34: =+F31-F32-F33 -> #REF! | G34: =+G31-G32-G33 -> #REF! | H34: =+H31-H32-H33 -> #REF! | I34: =+I31-I32-I33 -> #REF! | J34: =+J31-J32-J33 -> #REF!
B35: Tax | C35: ='Tax Calulator - Ref'!C46 -> 0 | D35: ='Tax Calulator - Ref'!D46 -> 0 | E35: ='Tax Calulator - Ref'!E46 -> 0 | F35: ='Tax Calulator - Ref'!F46 -> #REF! | G35: ='Tax Calulator - Ref'!G46 -> #REF! | H35: ='Tax Calulator - Ref'!H46 -> #REF! | I35: ='Tax Calulator - Ref'!I46 -> #REF! | J35: ='Tax Calulator - Ref'!J46 -> #REF!
B36: Profit After Tax | C36: =+C34-C35 -> -16.546 | D36: =+D34-D35 -> -16.784 | E36: =+E34-E35 -> -18.097 | F36: =+F34-F35 -> #REF! | G36: =+G34-G35 -> #REF! | H36: =+H34-H35 -> #REF! | I36: =+I34-I35 -> #REF! | J36: =+J34-J35 -> #REF!
B37: Depreciation | C37: =+C13 -> 3.47 | D37: =+D13 -> 3.4 | E37: =+E13 -> 3.4 | F37: =+F13 -> #REF! | G37: =+G13 -> #REF! | H37: =+H13 -> #REF! | I37: =+I13 -> #REF! | J37: =+J13 -> #REF!
B38: DSCR Calculation - Case II
B39: PAT | C39: =+C36 -> -16.546 | D39: =+D36 -> -16.784 | E39: =+E36 -> -18.097 | F39: =+F36 -> #REF! | G39: =+G36 -> #REF! | H39: =+H36 -> #REF! | I39: =+I36 -> #REF! | J39: =+J36 -> #REF!
B40: Depreciation | C40: =+C37 -> 3.47 | D40: =+D37 -> 3.4 | E40: =+E37 -> 3.4 | F40: =+F37 -> #REF! | G40: =+G37 -> #REF! | H40: =+H37 -> #REF! | I40: =+I37 -> #REF! | J40: =+J37 -> #REF!
B41: Interest on LTB | C41: =+C17 -> 0.6 | D41: =+D17 -> 0.21 | E41: =+E17 -> 0.12 | F41: =+F17 -> #REF! | G41: =+G17 -> #REF! | H41: =+H17 -> #REF! | I41: =+I17 -> #REF! | J41: =+J17 -> #REF!
B42: Deferred Tax Liability | C42: ='Tax Calulator - Ref'!C47 -> -1.1258415 | D42: ='Tax Calulator - Ref'!D47 -> -1.10313 | E42: ='Tax Calulator - Ref'!E47 -> -1.10313 | F42: ='Tax Calulator - Ref'!F47 -> #REF! | G42: ='Tax Calulator - Ref'!G47 -> #REF! | H42: ='Tax Calulator - Ref'!H47 -> #REF! | I42: ='Tax Calulator - Ref'!I47 -> #REF! | J42: ='Tax Calulator - Ref'!J47 -> #REF!
B43: Total A | C43: =SUM(C39:C42) -> -13.601842 | D43: =SUM(D39:D42) -> -14.27713 | E43: =SUM(E39:E42) -> -15.68013 | F43: =SUM(F39:F42) -> #REF! | G43: =SUM(G39:G42) -> #REF! | H43: =SUM(H39:H42) -> #REF! | I43: =SUM(I39:I42) -> #REF! | J43: =SUM(J39:J42) -> #REF!
B44: Interest on LTB | C44: =+C41 -> 0.6 | D44: =+D41 -> 0.21 | E44: =+E41 -> 0.12 | F44: =+F41 -> #REF! | G44: =+G41 -> #REF! | H44: =+H41 -> #REF! | I44: =+I41 -> #REF! | J44: =+J41 -> #REF!
B45: Principle Repayment | C45: =+C21 -> 2.42 | D45: =+D21 -> 2.39 | E45: =+E21 -> 1.02 | F45: =+F21 -> 1.02 | G45: =+G21 -> #REF! | H45: =+H21 -> #REF! | I45: =+I21 -> #REF! | J45: =+J21 -> #REF!
B46: Total B | C46: =SUM(C44:C45) -> 3.02 | D46: =SUM(D44:D45) -> 2.6 | E46: =SUM(E44:E45) -> 1.14 | F46: =SUM(F44:F45) -> #REF! | G46: =SUM(G44:G45) -> #REF! | H46: =SUM(H44:H45) -> #REF! | I46: =SUM(I44:I45) -> #REF! | J46: =SUM(J44:J45) -> #REF!
B47: DSCR (A/B) | C47: =+C43/C46 -> -4.503921 | D47: =+D43/D46 -> -5.4912038 | E47: =+E43/E46 -> -13.7545 | F47: =+F43/F46 -> #REF! | G47: =+G43/G46 -> #REF! | H47: =+H43/H46 -> #REF! | I47: =+I43/I46 -> #REF! | J47: =+J43/J46 -> #REF!
B48: Avg. DSCR (∑A/∑B) | C48: =SUM(C43:J43)/SUM(C46:J46) -> #REF!
B49: IRR Calculation - Case II
B50: Cost of Project | C50: ='DSCR & IRR'!B21 -> #VALUE! | D50: ='DSCR & IRR'!C21 -> 0 | E50: ='DSCR & IRR'!D21 -> 0 | F50: ='DSCR & IRR'!E21 -> 0 | G50: ='DSCR & IRR'!F21 -> 0 | H50: ='DSCR & IRR'!G21 -> 0 | I50: ='DSCR & IRR'!H21 -> 0 | J50: ='DSCR & IRR'!I21 -> 0
B51: Cash Inflow | C51: =+C43-C41 -> -14.201842 | D51: =+D43-D41 -> -14.48713 | E51: =+E43-E41 -> -15.80013 | F51: =+F43-F41 -> #REF! | G51: =+G43-G41 -> #REF! | H51: =+H43-H41 -> #REF! | I51: =+I43-I41 -> #REF! | J51: =+J43-J41 -> #REF! | K51: ='DSCR & IRR'!M23 -> #REF!
B52: IRR - Case II | C52: =K51 -> #REF!

Sheet Tax Calulator - Ref
A1: =+'Data Input'!B5 -> Punjab National Bank
A2: =+'Data Input'!B6 -> MCC Durgapur
A3: =+'Data Input'!B7 -> Durgapur
A4: =+'Data Input'!B4 -> H R Ispat Pvt Ltd
A5: TAX CALCULATOR | C5: =IF('Data Input'!I10="", "", 'Data Input'!I10) -> Audited | D5: =IF('Data Input'!J10="", "", 'Data Input'!J10) -> Audited | E5: =IF('Data Input'!K10="", "", 'Data Input'!K10) -> Projected | F5: =IF('Data Input'!L10="", "", 'Data Input'!L10) -> Projected | G5: =IF('Data Input'!#REF!="", "", 'Data Input'!#REF!) -> #REF! | H5: =IF('Data Input'!#REF!="", "", 'Data Input'!#REF!) -> #REF! | I5: =IF('Data Input'!#REF!="", "", 'Data Input'!#REF!) -> #REF! | J5: =IF('Data Input'!#REF!="", "", 'Data Input'!#REF!) -> #REF!
A6: General Case | C6: =IF('Data Input'!J11="", "", 'Data Input'!J11) -> 2024 | D6: =IF('Data Input'!K11="", "", 'Data Input'!K11) -> 2025 | E6: =IF('Data Input'!L11="", "", 'Data Input'!L11) -> 2026 | F6: =IF('Data Input'!#REF!="", "", 'Data Input'!#REF!) -> #REF! | G6: =IF('Data Input'!#REF!="", "", 'Data Input'!#REF!) -> #REF! | H6: =IF('Data Input'!#REF!="", "", 'Data Input'!#REF!) -> #REF! | I6: =IF('Data Input'!#REF!="", "", 'Data Input'!#REF!) -> #REF! | J6: =IF('Data Input'!#REF!="", "", 'Data Input'!#REF!) -> #REF!
A7: PBT | C7: =+'Data Input'!J54 -> 7.01 | D7: =+'Data Input'!K54 -> 9.66 | E7: =+'Data Input'!L54 -> 12.1 | F7: =+'Data Input'!#REF! -> #REF! | G7: =+'Data Input'!#REF! -> #REF! | H7: =+'Data Input'!#REF! -> #REF! | I7: =+'Data Input'!#REF! -> #REF! | J7: =+'Data Input'!#REF! -> #REF!
A8: Add: Depreciation as per Co's Act | C8: =+'Data Input'!J29 -> 3.47 | D8: =+'Data Input'!K29 -> 3.4 | E8: =+'Data Input'!L29 -> 3.4 | F8: =+'Data Input'!#REF! -> #REF! | G8: =+'Data Input'!#REF! -> #REF! | H8: =+'Data Input'!#REF! -> #REF! | I8: =+'Data Input'!#REF! -> #REF! | J8: =+'Data Input'!#REF! -> #REF!
A9: Less: Depreciation as per IT Act | C9: ='Data Input'!J144 -> 0 | D9: ='Data Input'!K144 -> 0 | E9: ='Data Input'!L144 -> 0 | F9: ='Data Input'!#REF! -> #REF! | G9: ='Data Input'!#REF! -> #REF! | H9: ='Data Input'!#REF! -> #REF! | I9: ='Data Input'!#REF! -> #REF! | J9: ='Data Input'!#REF! -> #REF!
A10: Adjusted PBT | C10: =C7+C8-C9 -> 10.48 | D10: =D7+D8-D9 -> 13.06 | E10: =E7+E8-E9 -> 15.5 | F10: =F7+F8-F9 -> #REF! | G10: =G7+G8-G9 -> #REF! | H10: =H7+H8-H9 -> #REF! | I10: =I7+I8-I9 -> #REF! | J10: =J7+J8-J9 -> #REF!
A11: Carried Forward Losses | C11: =IF((C10+B11)<0,(C10+B11),0) -> 0 | D11: =IF((D10+C11)<0,(D10+C11),0) -> 0 | E11: =IF((E10+D11)<0,(E10+D11),0) -> 0 | F11: =IF((F10+E11)<0,(F10+E11),0) -> #REF! | G11: =IF((G10+F11)<0,(G10+F11),0) -> #REF! | H11: =IF((H10+G11)<0,(H10+G11),0) -> #REF! | I11: =IF((I10+H11)<0,(I10+H11),0) -> #REF! | J11: =IF((J10+I11)<0,(J10+I11),0) -> #REF!
A12: Taxable Profit | C12: =IF((C10+B12)<0,0,(C10+B12)) -> 10.48 | D12: =IF((D10+C12)<0,0,(D10+C12)) -> 23.54 | E12: =IF((E10+D12)<0,0,(E10+D12)) -> 39.04 | F12: =IF((F10+E12)<0,0,(F10+E12)) -> #REF! | G12: =IF((G10+F12)<0,0,(G10+F12)) -> #REF! | H12: =IF((H10+G12)<0,0,(H10+G12)) -> #REF! | I12: =IF((I10+H12)<0,0,(I10+H12)) -> #REF! | J12: =IF((J10+I12)<0,0,(J10+I12)) -> #REF!
A13: Book Profit | C13: =C10 -> 10.48 | D13: =D10 -> 13.06 | E13: =E10 -> 15.5 | F13: =F10 -> #REF! | G13: =G10 -> #REF! | H13: =H10 -> #REF! | I13: =I10 -> #REF! | J13: =J10 -> #REF!
A14: Tax as per MAT | C14: =IF(C13<0,0,C13*C18) -> 2.0968122 | D14: =IF(D13<0,0,D13*D18) -> 2.6130122 | E14: =IF(E13<0,0,E13*E18) -> 3.1012013 | F14: =IF(F13<0,0,F13*F18) -> #REF! | G14: =IF(G13<0,0,G13*G18) -> #REF! | H14: =IF(H13<0,0,H13*H18) -> #REF! | I14: =IF(I13<0,0,I13*I18) -> #REF! | J14: =IF(J13<0,0,J13*J18) -> #REF!
A15: Normal Tax | C15: =IF(C12<0,0,C12*C19) -> 3.400236 | D15: =IF(D12<0,0,D12*D19) -> 7.637553 | E15: =IF(E12<0,0,E12*E19) -> 12.666528 | F15: =IF(F12<0,0,F12*F19) -> #REF! | G15: =IF(G12<0,0,G12*G19) -> #REF! | H15: =IF(H12<0,0,H12*H19) -> #REF! | I15: =IF(I12<0,0,I12*I19) -> #REF! | J15: =IF(J12<0,0,J12*J19) -> #REF!
A16: Tax Liability Payable | C16: =MAX(C14:C15) -> 3.400236 | D16: =MAX(D14:D15) -> 7.637553 | E16: =MAX(E14:E15) -> 12.666528 | F16: =MAX(F14:F15) -> #REF! | G16: =MAX(G14:G15) -> #REF! | H16: =MAX(H14:H15) -> #REF! | I16: =MAX(I14:I15) -> #REF! | J16: =MAX(J14:J15) -> #REF!
A17: Deferred Tax Liability | C17: =(C9-C8)*C19 -> -1.1258415 | D17: =(D9-D8)*D19 -> -1.10313 | E17: =(E9-E8)*E19 -> -1.10313 | F17: =(F9-F8)*F19 -> #REF! | G17: =(G9-G8)*G19 -> #REF! | H17: =(H9-H8)*H19 -> #REF! | I17: =(I9-I8)*I19 -> #REF! | J17: =(J9-J8)*J19 -> #REF!
A18: MAT rate | C18: =18.5%*105%*103% -> 0.2000775 | D18: =18.5%*105%*103% -> 0.2000775 | E18: =18.5%*105%*103% -> 0.2000775 | F18: =18.5%*105%*103% -> 0.2000775 | G18: =18.5%*105%*103% -> 0.2000775 | H18: =18.5%*105%*103% -> 0.2000775 | I18: =18.5%*105%*103% -> 0.2000775 | J18: =18.5%*105%*103% -> 0.2000775
A19: Normal Tax rate | C19: =30%*105%*103% -> 0.32445 | D19: =30%*105%*103% -> 0.32445 | E19: =30%*105%*103% -> 0.32445 | F19: =30%*105%*103% -> 0.32445 | G19: =30%*105%*103% -> 0.32445 | H19: =30%*105%*103% -> 0.32445 | I19: =30%*105%*103% -> 0.32445 | J19: =30%*105%*103% -> 0.32445
A20: TAX CALCULATOR | C20: =+C5 -> Audited | D20: =+D5 -> Audited | E20: =+E5 -> Projected | F20: =+F5 -> Projected | G20: =+G5 -> #REF! | H20: =+H5 -> #REF! | I20: =+I5 -> #REF! | J20: =+J5 -> #REF!
A21: Sensitivity Case I | C21: =+C6 -> 2024 | D21: =+D6 -> 2025 | E21: =+E6 -> 2026 | F21: =+F6 -> #REF! | G21: =+G6 -> #REF! | H21: =+H6 -> #REF! | I21: =+I6 -> #REF! | J21: =+J6 -> #REF!
A22: PBT | C22: =Sensitivity!C10 -> -12.2085 | D22: =Sensitivity!D10 -> -12.134 | E22: =Sensitivity!E10 -> -12.464 | F22: =Sensitivity!F10 -> #REF! | G22: =Sensitivity!G10 -> #REF! | H22: =Sensitivity!H10 -> #REF! | I22: =Sensitivity!I10 -> #REF! | J22: =Sensitivity!J10 -> #REF!
A23: Add: Depreciation as per Co's Act | C23: =+C8 -> 3.47 | D23: =+D8 -> 3.4 | E23: =+E8 -> 3.4 | F23: =+F8 -> #REF! | G23: =+G8 -> #REF! | H23: =+H8 -> #REF! | I23: =+I8 -> #REF! | J23: =+J8 -> #REF!
A24: Less: Depreciation as per IT Act | C24: =+C9 -> 0 | D24: =+D9 -> 0 | E24: =+E9 -> 0 | F24: =+F9 -> #REF! | G24: =+G9 -> #REF! | H24: =+H9 -> #REF! | I24: =+I9 -> #REF! | J24: =+J9 -> #REF!
A25: Adjusted PBT | C25: =C22+C23-C24 -> -8.7385 | D25: =D22+D23-D24 -> -8.734 | E25: =E22+E23-E24 -> -9.064 | F25: =F22+F23-F24 -> #REF! | G25: =G22+G23-G24 -> #REF! | H25: =H22+H23-H24 -> #REF! | I25: =I22+I23-I24 -> #REF! | J25: =J22+J23-J24 -> #REF!
A26: Carried Forward Losses | C26: =IF((C25+B26)<0,(C25+B26),0) -> -8.7385 | D26: =IF((D25+C26)<0,(D25+C26),0) -> -17.4725 | E26: =IF((E25+D26)<0,(E25+D26),0) -> -26.5365 | F26: =IF((F25+E26)<0,(F25+E26),0) -> #REF! | G26: =IF((G25+F26)<0,(G25+F26),0) -> #REF! | H26: =IF((H25+G26)<0,(H25+G26),0) -> #REF! | I26: =IF((I25+H26)<0,(I25+H26),0) -> #REF! | J26: =IF((J25+I26)<0,(J25+I26),0) -> #REF!
A27: Taxable Profit | C27: =IF((C25+B27)<0,0,(C25+B27)) -> 0 | D27: =IF((D25+C26)<0,0,(D25+C26)) -> 0 | E27: =IF((E25+D26)<0,0,(E25+D26)) -> 0 | F27: =IF((F25+E26)<0,0,(F25+E26)) -> #REF! | G27: =IF((G25+F26)<0,0,(G25+F26)) -> #REF! | H27: =IF((H25+G26)<0,0,(H25+G26)) -> #REF! | I27: =IF((I25+H26)<0,0,(I25+H26)) -> #REF! | J27: =IF((J25+I26)<0,0,(J25+I26)) -> #REF!
A28: Book Profit | C28: =C25 -> -8.7385 | D28: =D25 -> -8.734 | E28: =E25 -> -9.064 | F28: =F25 -> #REF! | G28: =G25 -> #REF! | H28: =H25 -> #REF! | I28: =I25 -> #REF! | J28: =J25 -> #REF!
A29: Tax as per MAT | C29: =IF(C28<0,0,C28*C33) -> 0 | D29: =IF(D28<0,0,D28*D33) -> 0 | E29: =IF(E28<0,0,E28*E33) -> 0 | F29: =IF(F28<0,0,F28*F33) -> #REF! | G29: =IF(G28<0,0,G28*G33) -> #REF! | H29: =IF(H28<0,0,H28*H33) -> #REF! | I29: =IF(I28<0,0,I28*I33) -> #REF! | J29: =IF(J28<0,0,J28*J33) -> #REF!
A30: Normal Tax | C30: =IF(C27<0,0,C27*C34) -> 0 | D30: =IF(D27<0,0,D27*D34) -> 0 | E30: =IF(E27<0,0,E27*E34) -> 0 | F30: =IF(F27<0,0,F27*F34) -> #REF! | G30: =IF(G27<0,0,G27*G34) -> #REF! | H30: =IF(H27<0,0,H27*H34) -> #REF! | I30: =IF(I27<0,0,I27*I34) -> #REF! | J30: =IF(J27<0,0,J27*J34) -> #REF!
A31: Tax Liability Payable | C31: =MAX(C29:C30) -> 0 | D31: =MAX(D29:D30) -> 0 | E31: =MAX(E29:E30) -> 0 | F31: =MAX(F29:F30) -> #REF! | G31: =MAX(G29:G30) -> #REF! | H31: =MAX(H29:H30) -> #REF! | I31: =MAX(I29:I30) -> #REF! | J31: =MAX(J29:J30) -> #REF!
A32: Deferred Tax Liability | C32: =(C24-C23)*C34 -> -1.1258415 | D32: =(D24-D23)*D34 -> -1.10313 | E32: =(E24-E23)*E34 -> -1.10313 | F32: =(F24-F23)*F34 -> #REF! | G32: =(G24-G23)*G34 -> #REF! | H32: =(H24-H23)*H34 -> #REF! | I32: =(I24-I23)*I34 -> #REF! | J32: =(J24-J23)*J34 -> #REF!
A33: MAT rate | C33: =18.5%*105%*103% -> 0.2000775 | D33: =18.5%*105%*103% -> 0.2000775 | E33: =18.5%*105%*103% -> 0.2000775 | F33: =18.5%*105%*103% -> 0.2000775 | G33: =18.5%*105%*103% -> 0.2000775 | H33: =18.5%*105%*103% -> 0.2000775 | I33: =18.5%*105%*103% -> 0.2000775 | J33: =18.5%*105%*103% -> 0.2000775
A34: Normal Tax rate | C34: =30%*105%*103% -> 0.32445 | D34: =30%*105%*103% -> 0.32445 | E34: =30%*105%*103% -> 0.32445 | F34: =30%*105%*103% -> 0.32445 | G34: =30%*105%*103% -> 0.32445 | H34: =30%*105%*103% -> 0.32445 | I34: =30%*105%*103% -> 0.32445 | J34: =30%*105%*103% -> 0.32445
A35: TAX CALCULATOR | C35: =+C20 -> Audited | D35: =+D20 -> Audited | E35: =+E20 -> Projected | F35: =+F20 -> Projected | G35: =+G20 -> #REF! | H35: =+H20 -> #REF! | I35: =+I20 -> #REF! | J35: =+J20 -> #REF!
A36: Sensitivity Case II | C36: =+C21 -> 2024 | D36: =+D21 -> 2025 | E36: =+E21 -> 2026 | F36: =+F21 -> #REF! | G36: =+G21 -> #REF! | H36: =+H21 -> #REF! | I36: =+I21 -> #REF! | J36: =+J21 -> #REF!
A37: PBT | C37: =Sensitivity!C34 -> -16.546 | D37: =Sensitivity!D34 -> -16.784 | E37: =Sensitivity!E34 -> -18.097 | F37: =Sensitivity!F34 -> #REF! | G37: =Sensitivity!G34 -> #REF! | H37: =Sensitivity!H34 -> #REF! | I37: =Sensitivity!I34 -> #REF! | J37: =Sensitivity!J34 -> #REF!
A38: Add: Depreciation as per Co's Act | C38: =+C23 -> 3.47 | D38: =+D23 -> 3.4 | E38: =+E23 -> 3.4 | F38: =+F23 -> #REF! | G38: =+G23 -> #REF! | H38: =+H23 -> #REF! | I38: =+I23 -> #REF! | J38: =+J23 -> #REF!
A39: Less: Depreciation as per IT Act | C39: =+C24 -> 0 | D39: =+D24 -> 0 | E39: =+E24 -> 0 | F39: =+F24 -> #REF! | G39: =+G24 -> #REF! | H39: =+H24 -> #REF! | I39: =+I24 -> #REF! | J39: =+J24 -> #REF!
A40: Adjusted PBT | C40: =C37+C38-C39 -> -13.076 | D40: =D37+D38-D39 -> -13.384 | E40: =E37+E38-E39 -> -14.697 | F40: =F37+F38-F39 -> #REF! | G40: =G37+G38-G39 -> #REF! | H40: =H37+H38-H39 -> #REF! | I40: =I37+I38-I39 -> #REF! | J40: =J37+J38-J39 -> #REF!
A41: Carried Forward Losses | C41: =IF((C40+B41)<0,(C40+B41),0) -> -13.076 | D41: =IF((D40+C41)<0,(D40+C41),0) -> -26.46 | E41: =IF((E40+D41)<0,(E40+D41),0) -> -41.157 | F41: =IF((F40+E41)<0,(F40+E41),0) -> #REF! | G41: =IF((G40+F41)<0,(G40+F41),0) -> #REF! | H41: =IF((H40+G41)<0,(H40+G41),0) -> #REF! | I41: =IF((I40+H41)<0,(I40+H41),0) -> #REF! | J41: =IF((J40+I41)<0,(J40+I41),0) -> #REF!
A42: Taxable Profit | C42: =IF((C40+B42)<0,0,(C40+B42)) -> 0 | D42: =IF((D40+C41)<0,0,(D40+C41)) -> 0 | E42: =IF((E40+D41)<0,0,(E40+D41)) -> 0 | F42: =IF((F40+E41)<0,0,(F40+E41)) -> #REF! | G42: =IF((G40+F41)<0,0,(G40+F41)) -> #REF! | H42: =IF((H40+G41)<0,0,(H40+G41)) -> #REF! | I42: =IF((I40+H41)<0,0,(I40+H41)) -> #REF! | J42: =IF((J40+I41)<0,0,(J40+I41)) -> #REF!
A43: Book Profit | C43: =C40 -> -13.076 | D43: =D40 -> -13.384 | E43: =E40 -> -14.697 | F43: =F40 -> #REF! | G43: =G40 -> #REF! | H43: =H40 -> #REF! | I43: =I40 -> #REF! | J43: =J40 -> #REF!
A44: Tax as per MAT | C44: =IF(C43<0,0,C43*C48) -> 0 | D44: =IF(D43<0,0,D43*D48) -> 0 | E44: =IF(E43<0,0,E43*E48) -> 0 | F44: =IF(F43<0,0,F43*F48) -> #REF! | G44: =IF(G43<0,0,G43*G48) -> #REF! | H44: =IF(H43<0,0,H43*H48) -> #REF! | I44: =IF(I43<0,0,I43*I48) -> #REF! | J44: =IF(J43<0,0,J43*J48) -> #REF!
A45: Normal Tax | C45: =IF(C42<0,0,C42*C49) -> 0 | D45: =IF(D42<0,0,D42*D49) -> 0 | E45: =IF(E42<0,0,E42*E49) -> 0 | F45: =IF(F42<0,0,F42*F49) -> #REF! | G45: =IF(G42<0,0,G42*G49) -> #REF! | H45: =IF(H42<0,0,H42*H49) -> #REF! | I45: =IF(I42<0,0,I42*I49) -> #REF! | J45: =IF(J42<0,0,J42*J49) -> #REF!
A46: Tax Liability Payable | C46: =MAX(C44:C45) -> 0 | D46: =MAX(D44:D45) -> 0 | E46: =MAX(E44:E45) -> 0 | F46: =MAX(F44:F45) -> #REF! | G46: =MAX(G44:G45) -> #REF! | H46: =MAX(H44:H45) -> #REF! | I46: =MAX(I44:I45) -> #REF! | J46: =MAX(J44:J45) -> #REF!
A47: Deferred Tax Liability | C47: =(C39-C38)*C49 -> -1.1258415 | D47: =(D39-D38)*D49 -> -1.10313 | E47: =(E39-E38)*E49 -> -1.10313 | F47: =(F39-F38)*F49 -> #REF! | G47: =(G39-G38)*G49 -> #REF! | H47: =(H39-H38)*H49 -> #REF! | I47: =(I39-I38)*I49 -> #REF! | J47: =(J39-J38)*J49 -> #REF!
A48: MAT rate | C48: =18.5%*105%*103% -> 0.2000775 | D48: =18.5%*105%*103% -> 0.2000775 | E48: =18.5%*105%*103% -> 0.2000775 | F48: =18.5%*105%*103% -> 0.2000775 | G48: =18.5%*105%*103% -> 0.2000775 | H48: =18.5%*105%*103% -> 0.2000775 | I48: =18.5%*105%*103% -> 0.2000775 | J48: =18.5%*105%*103% -> 0.2000775
A49: Normal Tax rate | C49: =30%*105%*103% -> 0.32445 | D49: =30%*105%*103% -> 0.32445 | E49: =30%*105%*103% -> 0.32445 | F49: =30%*105%*103% -> 0.32445 | G49: =30%*105%*103% -> 0.32445 | H49: =30%*105%*103% -> 0.32445 | I49: =30%*105%*103% -> 0.32445 | J49: =30%*105%*103% -> 0.32445

Sheet Sheet1
A2: Rajendra Bharuka (HUF) | B2: 1751386 | C2: =B2/B12% -> 7.3830139
A3: Pritesh Dinesh Bharuka | B3: 2372183 | C3: =B3/$B$12% -> 10
A4: Renu Rajendra Bharuka | B4: 3558274 | C4: =B4/$B$12% -> 14.999998
A5: Dinesh Satyanarayan Bharuka (HUF) | B5: 1167591 | C5: =B5/$B$12% -> 4.9220107
A6: Dinesh Satyanarayan Bharuka | B6: 3783193 | C6: =B6/$B$12% -> 15.94815
A7: Lokesh Rajendra Bhaurka | B7: 2010848 | C7: =B7/$B$12% -> 8.4767828
A8: Rajendra Satyanarayan Bharuka | B8: 2040407 | C8: =B8/$B$12% -> 8.6013895
A9: Santosh Dinesh Bharuka | B9: 1932247 | C9: =B9/$B$12% -> 8.1454382
A10: Nilesh Dinesh Bharuka | B10: 2605701 | C10: =B10/$B$12% -> 10.984401
A11: Sneha Lokesh Bharuka | B11: 2500000 | C11: =B11/$B$12% -> 10.538816
A12: Total | B12: 23721830

Sheet Sheet2
